{
  "type": "Feature",
  "properties": {
    "gn:admin1_code":"0.0",
    "gn:asciiname":"Sondina",
    "gn:country_code":"TG",
    "gn:dem":268,
    "gn:feature_class":"P",
    "gn:feature_code":"PPL",
    "gn:name":"Sondina",
    "gn:population":0,
    "gn:timezone":"Africa/Lome",
    "iso:country":"TG",
    "wof:name":"Sondina",
    "wof:placetype":"locality"
},
  "geometry": {"coordinates":[0.98333,9.48333],"type":"Point"}
}