{
  "type": "Feature",
  "properties": {
    "gn:admin1_code":"24.0",
    "gn:asciiname":"Azyagbang",
    "gn:country_code":"TG",
    "gn:dem":24,
    "gn:feature_class":"P",
    "gn:feature_code":"PPL",
    "gn:name":"Azyagbang",
    "gn:population":0,
    "gn:timezone":"Africa/Lome",
    "iso:country":"TG",
    "wof:name":"Azyagbang",
    "wof:placetype":"locality"
},
  "geometry": {"coordinates":[1.20028,6.17722],"type":"Point"}
}