{
  "type": "Feature",
  "properties": {
    "gn:admin1_code":"0.0",
    "gn:asciiname":"Ankoukope",
    "gn:country_code":"TG",
    "gn:dem":76,
    "gn:feature_class":"P",
    "gn:feature_code":"PPL",
    "gn:name":"Ankoukop\u00e9",
    "gn:population":0,
    "gn:timezone":"Africa/Lome",
    "iso:country":"TG",
    "wof:name":"Ankoukope",
    "wof:placetype":"locality"
},
  "geometry": {"coordinates":[0.73333,6.51667],"type":"Point"}
}