{
  "type": "Feature",
  "properties": {
    "gn:admin1_code":"0.0",
    "gn:asciiname":"Namongou",
    "gn:country_code":"TG",
    "gn:dem":256,
    "gn:feature_class":"P",
    "gn:feature_code":"PPL",
    "gn:name":"Namongou",
    "gn:population":0,
    "gn:timezone":"Africa/Lome",
    "iso:country":"TG",
    "wof:name":"Namongou",
    "wof:placetype":"locality"
},
  "geometry": {"coordinates":[0.23333,10.91667],"type":"Point"}
}