{
  "type": "Feature",
  "properties": {
    "gn:admin1_code":"0.0",
    "gn:asciiname":"Klonou",
    "gn:country_code":"TG",
    "gn:dem":174,
    "gn:feature_class":"P",
    "gn:feature_code":"PPL",
    "gn:name":"Klonou",
    "gn:population":0,
    "gn:timezone":"Africa/Lome",
    "iso:country":"TG",
    "wof:name":"Klonou",
    "wof:placetype":"locality"
},
  "geometry": {"coordinates":[0.68333,6.83333],"type":"Point"}
}