{
  "type": "Feature",
  "properties": {
    "gn:admin1_code":"24.0",
    "gn:asciiname":"Naka",
    "gn:country_code":"TG",
    "gn:dem":44,
    "gn:feature_class":"P",
    "gn:feature_code":"PPL",
    "gn:name":"Naka",
    "gn:population":0,
    "gn:timezone":"Africa/Lome",
    "iso:country":"TG",
    "name:ceb_x_preferred":[
        "Naka"
    ],
    "name:deu_x_preferred":[
        "Naka"
    ],
    "name:fin_x_preferred":[
        "Naka"
    ],
    "name:fra_x_preferred":[
        "Naka"
    ],
    "name:hun_x_preferred":[
        "Naka"
    ],
    "name:mlg_x_preferred":[
        "Naka"
    ],
    "name:nep_x_preferred":[
        "\u0928\u093e\u0915"
    ],
    "name:nld_x_preferred":[
        "Naka"
    ],
    "name:pol_x_preferred":[
        "Naka"
    ],
    "name:ron_x_preferred":[
        "Naka"
    ],
    "name:rus_x_preferred":[
        "\u041d\u0430\u043a\u0430"
    ],
    "name:spa_x_preferred":[
        "Naka"
    ],
    "name:swe_x_preferred":[
        "Naka"
    ],
    "name:ukr_x_preferred":[
        "\u041d\u0430\u043a\u0430"
    ],
    "wof:name":"Naka",
    "wof:placetype":"locality"
},
  "geometry": {"coordinates":[1.11194,6.23889],"type":"Point"}
}