{
  "type": "Feature",
  "properties": {
    "gn:admin1_code":"0.0",
    "gn:asciiname":"Petchikoe",
    "gn:country_code":"TG",
    "gn:dem":99,
    "gn:feature_class":"P",
    "gn:feature_code":"PPL",
    "gn:name":"Petchiko\u00e9",
    "gn:population":0,
    "gn:timezone":"Africa/Lome",
    "iso:country":"TG",
    "wof:name":"Petchikoe",
    "wof:placetype":"locality"
},
  "geometry": {"coordinates":[1.51667,7.16667],"type":"Point"}
}