{
  "type": "Feature",
  "properties": {
    "gn:admin1_code":"0.0",
    "gn:asciiname":"Insandiapo",
    "gn:cc2":"TG",
    "gn:country_code":"TG",
    "gn:dem":169,
    "gn:feature_class":"P",
    "gn:feature_code":"PPL",
    "gn:name":"Insandiapo",
    "gn:population":0,
    "gn:timezone":"Africa/Lome",
    "iso:country":"TG",
    "name:und_x_variant":[
        "Isandiapo",
        "Insandiapo"
    ],
    "wof:name":"Insandiapo",
    "wof:placetype":"locality"
},
  "geometry": {"coordinates":[0.56667,9.61667],"type":"Point"}
}