{
  "type": "Feature",
  "properties": {
    "gn:admin1_code":"0.0",
    "gn:asciiname":"Ayata",
    "gn:country_code":"TG",
    "gn:dem":32,
    "gn:feature_class":"P",
    "gn:feature_code":"PPL",
    "gn:name":"Ayata",
    "gn:population":0,
    "gn:timezone":"Africa/Lome",
    "iso:country":"TG",
    "name:deu_x_preferred":[
        "Ayata"
    ],
    "name:que_x_preferred":[
        "Ayata"
    ],
    "wof:name":"Ayata",
    "wof:placetype":"locality"
},
  "geometry": {"coordinates":[1.56667,6.33333],"type":"Point"}
}