{
  "type": "Feature",
  "properties": {
    "gn:admin1_code":"0.0",
    "gn:asciiname":"Koukpan",
    "gn:cc2":"TG",
    "gn:country_code":"TG",
    "gn:dem":113,
    "gn:feature_class":"P",
    "gn:feature_code":"PPL",
    "gn:name":"Koukpan",
    "gn:population":0,
    "gn:timezone":"Africa/Lome",
    "iso:country":"TG",
    "name:und_x_variant":[
        "Kukub",
        "Koupou",
        "Koukpam",
        "Kupone",
        "Kupon",
        "Koukbon",
        "Koukpan"
    ],
    "wof:name":"Koukpan",
    "wof:placetype":"locality"
},
  "geometry": {"coordinates":[0.28333,9.46667],"type":"Point"}
}