{
  "type": "Feature",
  "properties": {
    "gn:admin1_code":"0.0",
    "gn:asciiname":"Betekpo",
    "gn:country_code":"TG",
    "gn:dem":114,
    "gn:feature_class":"P",
    "gn:feature_code":"PPL",
    "gn:name":"B\u00e9t\u00e9kpo",
    "gn:population":0,
    "gn:timezone":"Africa/Lome",
    "iso:country":"TG",
    "wof:name":"Betekpo",
    "wof:placetype":"locality"
},
  "geometry": {"coordinates":[1.45,7.06667],"type":"Point"}
}