{
  "type": "Feature",
  "properties": {
    "gn:admin1_code":"0.0",
    "gn:asciiname":"Filandi",
    "gn:country_code":"TG",
    "gn:dem":342,
    "gn:feature_class":"P",
    "gn:feature_code":"PPL",
    "gn:name":"Filandi",
    "gn:population":0,
    "gn:timezone":"Africa/Lome",
    "iso:country":"TG",
    "wof:name":"Filandi",
    "wof:placetype":"locality"
},
  "geometry": {"coordinates":[1.16667,9.43333],"type":"Point"}
}