{
  "type": "Feature",
  "properties": {
    "gn:admin1_code":"24.0",
    "gn:asciiname":"Azongo",
    "gn:country_code":"TG",
    "gn:dem":37,
    "gn:feature_class":"P",
    "gn:feature_code":"PPL",
    "gn:name":"Azongo",
    "gn:population":0,
    "gn:timezone":"Africa/Lome",
    "iso:country":"TG",
    "wof:name":"Azongo",
    "wof:placetype":"locality"
},
  "geometry": {"coordinates":[1.18639,6.21556],"type":"Point"}
}