{
  "type": "Feature",
  "properties": {
    "gn:admin1_code":"0.0",
    "gn:asciiname":"Awassa",
    "gn:country_code":"TG",
    "gn:dem":199,
    "gn:feature_class":"P",
    "gn:feature_code":"PPL",
    "gn:name":"Awassa",
    "gn:population":0,
    "gn:timezone":"Africa/Lome",
    "iso:country":"TG",
    "wof:name":"Awassa",
    "wof:placetype":"locality"
},
  "geometry": {"coordinates":[0.95,9.85],"type":"Point"}
}