{
  "type": "Feature",
  "properties": {
    "gn:admin1_code":"0.0",
    "gn:asciiname":"Gbemaho",
    "gn:country_code":"TG",
    "gn:dem":221,
    "gn:feature_class":"P",
    "gn:feature_code":"PPL",
    "gn:name":"Gb\u00e9maho",
    "gn:population":0,
    "gn:timezone":"Africa/Lome",
    "iso:country":"TG",
    "wof:name":"Gbemaho",
    "wof:placetype":"locality"
},
  "geometry": {"coordinates":[1.16667,7.48333],"type":"Point"}
}