{
  "type": "Feature",
  "properties": {
    "gn:admin1_code":"0.0",
    "gn:asciiname":"Houmblasso Kope",
    "gn:cc2":"TG",
    "gn:country_code":"TG",
    "gn:dem":65,
    "gn:feature_class":"P",
    "gn:feature_code":"PPL",
    "gn:name":"Houmblasso Kop\u00e9",
    "gn:population":0,
    "gn:timezone":"Africa/Lome",
    "iso:country":"TG",
    "name:und_x_variant":[
        "Hounbl\u00e9so Kop\u00e9",
        "Houmblasso Kop\u00e9"
    ],
    "wof:name":"Houmblasso Kope",
    "wof:placetype":"locality"
},
  "geometry": {"coordinates":[1.61667,6.48333],"type":"Point"}
}