{
  "type": "Feature",
  "properties": {
    "gn:admin1_code":"24.0",
    "gn:asciiname":"Sagbado",
    "gn:country_code":"TG",
    "gn:dem":36,
    "gn:feature_class":"P",
    "gn:feature_code":"PPL",
    "gn:name":"Sagbado",
    "gn:population":0,
    "gn:timezone":"Africa/Lome",
    "iso:country":"TG",
    "wof:name":"Sagbado",
    "wof:placetype":"locality"
},
  "geometry": {"coordinates":[1.1575,6.20361],"type":"Point"}
}