{
  "type": "Feature",
  "properties": {
    "gn:admin1_code":"0.0",
    "gn:asciiname":"Dozo",
    "gn:country_code":"TG",
    "gn:dem":178,
    "gn:feature_class":"P",
    "gn:feature_code":"PPL",
    "gn:name":"Dozo",
    "gn:population":0,
    "gn:timezone":"Africa/Lome",
    "iso:country":"TG",
    "wof:name":"Dozo",
    "wof:placetype":"locality"
},
  "geometry": {"coordinates":[0.95,10.23333],"type":"Point"}
}