{
  "type": "Feature",
  "properties": {
    "gn:admin1_code":"0.0",
    "gn:asciiname":"Djarakpana",
    "gn:cc2":"TG",
    "gn:country_code":"TG",
    "gn:dem":194,
    "gn:feature_class":"P",
    "gn:feature_code":"PPL",
    "gn:name":"Djarakpana",
    "gn:population":0,
    "gn:timezone":"Africa/Lome",
    "iso:country":"TG",
    "name:und_x_variant":[
        "Djereponi",
        "Djarakpana"
    ],
    "wof:name":"Djarakpana",
    "wof:placetype":"locality"
},
  "geometry": {"coordinates":[0.56667,8.78333],"type":"Point"}
}