{
  "type": "Feature",
  "properties": {
    "gn:admin1_code":"23.0",
    "gn:asciiname":"Lassa",
    "gn:country_code":"TG",
    "gn:dem":376,
    "gn:feature_class":"P",
    "gn:feature_code":"PPL",
    "gn:name":"Lassa",
    "gn:population":0,
    "gn:timezone":"Africa/Lome",
    "iso:country":"TG",
    "name:und_x_variant":[
        "Lasa",
        "Lassa"
    ],
    "wof:name":"Lassa",
    "wof:placetype":"locality"
},
  "geometry": {"coordinates":[1.24222,9.615],"type":"Point"}
}