{
  "type": "Feature",
  "properties": {
    "gn:admin1_code":"0.0",
    "gn:asciiname":"Biegou",
    "gn:country_code":"TG",
    "gn:dem":271,
    "gn:feature_class":"P",
    "gn:feature_code":"PPL",
    "gn:name":"Bi\u00e9gou",
    "gn:population":0,
    "gn:timezone":"Africa/Lome",
    "iso:country":"TG",
    "wof:name":"Biegou",
    "wof:placetype":"locality"
},
  "geometry": {"coordinates":[0.36667,10.71667],"type":"Point"}
}