{
  "type": "Feature",
  "properties": {
    "gn:admin1_code":"24.0",
    "gn:asciiname":"Doevi",
    "gn:country_code":"TG",
    "gn:dem":67,
    "gn:feature_class":"P",
    "gn:feature_code":"PPL",
    "gn:name":"Do\u00e9vi",
    "gn:population":0,
    "gn:timezone":"Africa/Lome",
    "iso:country":"TG",
    "wof:name":"Doevi",
    "wof:placetype":"locality"
},
  "geometry": {"coordinates":[1.3275,6.15528],"type":"Point"}
}