{
  "type": "Feature",
  "properties": {
    "gn:admin1_code":"23.0",
    "gn:asciiname":"Tenega",
    "gn:country_code":"TG",
    "gn:dem":427,
    "gn:feature_class":"P",
    "gn:feature_code":"PPL",
    "gn:name":"T\u00e9n\u00e9ga",
    "gn:population":0,
    "gn:timezone":"Africa/Lome",
    "iso:country":"TG",
    "name:und_x_variant":[
        "T\u00e9n\u00e9ga"
    ],
    "wof:name":"Tenega",
    "wof:placetype":"locality"
},
  "geometry": {"coordinates":[1.12806,9.82806],"type":"Point"}
}