{
  "type": "Feature",
  "properties": {
    "gn:admin1_code":"0.0",
    "gn:asciiname":"Djobedji Agokpo Tokpli",
    "gn:cc2":"TG",
    "gn:country_code":"TG",
    "gn:dem":131,
    "gn:feature_class":"P",
    "gn:feature_code":"PPL",
    "gn:name":"Djob\u00e9dji Agokpo Tokpli",
    "gn:population":0,
    "gn:timezone":"Africa/Lome",
    "iso:country":"TG",
    "name:und_x_variant":[
        "Agokp\u00e9",
        "Djob\u00e9dji Agokpo Tokpli"
    ],
    "wof:name":"Djobedji Agokpo Tokpli",
    "wof:placetype":"locality"
},
  "geometry": {"coordinates":[1.03333,6.68333],"type":"Point"}
}