{
  "type": "Feature",
  "properties": {
    "gn:admin1_code":"24.0",
    "gn:asciiname":"Azogenou",
    "gn:country_code":"TG",
    "gn:dem":30,
    "gn:feature_class":"P",
    "gn:feature_code":"PPL",
    "gn:name":"Azog\u00e9nou",
    "gn:population":0,
    "gn:timezone":"Africa/Lome",
    "iso:country":"TG",
    "wof:name":"Azogenou",
    "wof:placetype":"locality"
},
  "geometry": {"coordinates":[1.22806,6.19917],"type":"Point"}
}