{
  "type": "Feature",
  "properties": {
    "gn:admin1_code":"0.0",
    "gn:asciiname":"Aveho",
    "gn:cc2":"TG",
    "gn:country_code":"TG",
    "gn:dem":371,
    "gn:feature_class":"P",
    "gn:feature_code":"PPL",
    "gn:name":"Av\u00e9ho",
    "gn:population":0,
    "gn:timezone":"Africa/Lome",
    "iso:country":"TG",
    "name:und_x_variant":[
        "Av\u00e9ho-Tongb\u00e9",
        "Av\u00e9ho"
    ],
    "wof:name":"Aveho",
    "wof:placetype":"locality"
},
  "geometry": {"coordinates":[0.78333,7.21667],"type":"Point"}
}