{
  "type": "Feature",
  "properties": {
    "gn:admin1_code":"24.0",
    "gn:asciiname":"Hahatoe",
    "gn:country_code":"TG",
    "gn:dem":32,
    "gn:feature_class":"P",
    "gn:feature_code":"PPL",
    "gn:name":"Hahato\u00e9",
    "gn:population":0,
    "gn:timezone":"Africa/Lome",
    "iso:country":"TG",
    "name:und_x_variant":[
        "Hahot\u00e9",
        "Hahoto\u00e9",
        "Hahato\u00e9"
    ],
    "wof:name":"Hahatoe",
    "wof:placetype":"locality"
},
  "geometry": {"coordinates":[1.39056,6.36528],"type":"Point"}
}