{
  "type": "Feature",
  "properties": {
    "gn:admin1_code":"0.0",
    "gn:asciiname":"Apeda",
    "gn:country_code":"TG",
    "gn:dem":27,
    "gn:feature_class":"P",
    "gn:feature_code":"PPL",
    "gn:name":"Ap\u00e9da",
    "gn:population":0,
    "gn:timezone":"Africa/Lome",
    "iso:country":"TG",
    "wof:name":"Apeda",
    "wof:placetype":"locality"
},
  "geometry": {"coordinates":[1.63333,6.31667],"type":"Point"}
}