{
  "type": "Feature",
  "properties": {
    "gn:admin1_code":"0.0",
    "gn:asciiname":"Agoune",
    "gn:country_code":"TG",
    "gn:dem":237,
    "gn:feature_class":"P",
    "gn:feature_code":"PPL",
    "gn:name":"Agoun\u00e9",
    "gn:population":0,
    "gn:timezone":"Africa/Lome",
    "iso:country":"TG",
    "wof:name":"Agoune",
    "wof:placetype":"locality"
},
  "geometry": {"coordinates":[1.16667,7.63333],"type":"Point"}
}