{
  "type": "Feature",
  "properties": {
    "gn:admin1_code":"0.0",
    "gn:asciiname":"Essankope",
    "gn:country_code":"TG",
    "gn:dem":93,
    "gn:feature_class":"P",
    "gn:feature_code":"PPL",
    "gn:name":"Essankop\u00e9",
    "gn:population":0,
    "gn:timezone":"Africa/Lome",
    "iso:country":"TG",
    "wof:name":"Essankope",
    "wof:placetype":"locality"
},
  "geometry": {"coordinates":[0.73333,6.48333],"type":"Point"}
}