{
  "type": "Feature",
  "properties": {
    "gn:admin1_code":"0.0",
    "gn:asciiname":"Adakakpe",
    "gn:country_code":"TG",
    "gn:dem":107,
    "gn:feature_class":"P",
    "gn:feature_code":"PPL",
    "gn:name":"Adakakp\u00e9",
    "gn:population":0,
    "gn:timezone":"Africa/Lome",
    "iso:country":"TG",
    "wof:name":"Adakakpe",
    "wof:placetype":"locality"
},
  "geometry": {"coordinates":[1.18333,6.81667],"type":"Point"}
}