{
  "type": "Feature",
  "properties": {
    "gn:admin1_code":"0.0",
    "gn:asciiname":"Wonougba",
    "gn:country_code":"TG",
    "gn:dem":127,
    "gn:feature_class":"P",
    "gn:feature_code":"PPL",
    "gn:name":"Wonougba",
    "gn:population":0,
    "gn:timezone":"Africa/Lome",
    "iso:country":"TG",
    "wof:name":"Wonougba",
    "wof:placetype":"locality"
},
  "geometry": {"coordinates":[0.91667,6.75],"type":"Point"}
}