{
  "type": "Feature",
  "properties": {
    "gn:admin1_code":"24.0",
    "gn:asciiname":"Aoude",
    "gn:country_code":"TG",
    "gn:dem":48,
    "gn:feature_class":"P",
    "gn:feature_code":"PPL",
    "gn:name":"Aoud\u00e9",
    "gn:population":0,
    "gn:timezone":"Africa/Lome",
    "iso:country":"TG",
    "wof:name":"Aoude",
    "wof:placetype":"locality"
},
  "geometry": {"coordinates":[1.14833,6.23861],"type":"Point"}
}