{
  "type": "Feature",
  "properties": {
    "gn:admin1_code":"24.0",
    "gn:asciiname":"Sedjro",
    "gn:country_code":"TG",
    "gn:dem":25,
    "gn:feature_class":"P",
    "gn:feature_code":"PPL",
    "gn:name":"Sedjro",
    "gn:population":0,
    "gn:timezone":"Africa/Lome",
    "iso:country":"TG",
    "wof:name":"Sedjro",
    "wof:placetype":"locality"
},
  "geometry": {"coordinates":[1.185,6.18111],"type":"Point"}
}