{
  "type": "Feature",
  "properties": {
    "gn:admin1_code":"0.0",
    "gn:asciiname":"Bantierk",
    "gn:country_code":"TG",
    "gn:dem":212,
    "gn:feature_class":"P",
    "gn:feature_code":"PPL",
    "gn:name":"Bantierk",
    "gn:population":0,
    "gn:timezone":"Africa/Lome",
    "iso:country":"TG",
    "name:und_x_variant":[
        "Banntierk",
        "Bantierk"
    ],
    "wof:name":"Bantierk",
    "wof:placetype":"locality"
},
  "geometry": {"coordinates":[0.1745,10.59869],"type":"Point"}
}