{
  "type": "Feature",
  "properties": {
    "gn:admin1_code":"0.0",
    "gn:asciiname":"Niagbangbou",
    "gn:country_code":"TG",
    "gn:dem":168,
    "gn:feature_class":"P",
    "gn:feature_code":"PPL",
    "gn:name":"Niagbangbou",
    "gn:population":0,
    "gn:timezone":"Africa/Lome",
    "iso:country":"TG",
    "wof:name":"Niagbangbou",
    "wof:placetype":"locality"
},
  "geometry": {"coordinates":[0.53333,9.56667],"type":"Point"}
}