{
  "type": "Feature",
  "properties": {
    "gn:admin1_code":"0.0",
    "gn:asciiname":"Zonachrakope",
    "gn:country_code":"TG",
    "gn:dem":177,
    "gn:feature_class":"P",
    "gn:feature_code":"PPL",
    "gn:name":"Zonachrakop\u00e9",
    "gn:population":0,
    "gn:timezone":"Africa/Lome",
    "iso:country":"TG",
    "wof:name":"Zonachrakope",
    "wof:placetype":"locality"
},
  "geometry": {"coordinates":[1.41667,7.58333],"type":"Point"}
}