{
  "type": "Feature",
  "properties": {
    "gn:admin1_code":"24.0",
    "gn:asciiname":"Tahassi",
    "gn:country_code":"TG",
    "gn:dem":36,
    "gn:feature_class":"P",
    "gn:feature_code":"PPL",
    "gn:name":"Tahassi",
    "gn:population":0,
    "gn:timezone":"Africa/Lome",
    "iso:country":"TG",
    "name:und_x_variant":[
        "Tahasi",
        "Tansi",
        "Tahassi\u00e9",
        "Tahassi"
    ],
    "wof:name":"Tahassi",
    "wof:placetype":"locality"
},
  "geometry": {"coordinates":[1.34167,6.31806],"type":"Point"}
}