{
  "type": "Feature",
  "properties": {
    "gn:admin1_code":"0.0",
    "gn:asciiname":"Fazade",
    "gn:country_code":"TG",
    "gn:dem":473,
    "gn:feature_class":"P",
    "gn:feature_code":"PPL",
    "gn:name":"Fazad\u00e8",
    "gn:population":0,
    "gn:timezone":"Africa/Lome",
    "iso:country":"TG",
    "name:und_x_variant":[
        "Fazad\u00e8"
    ],
    "wof:name":"Fazade",
    "wof:placetype":"locality"
},
  "geometry": {"coordinates":[1.25,9.23333],"type":"Point"}
}