{
  "type": "Feature",
  "properties": {
    "gn:admin1_code":"0.0",
    "gn:asciiname":"Kodiokpegble",
    "gn:country_code":"TG",
    "gn:dem":257,
    "gn:feature_class":"P",
    "gn:feature_code":"PPL",
    "gn:name":"Kodiokp\u00e9gbl\u00e9",
    "gn:population":0,
    "gn:timezone":"Africa/Lome",
    "iso:country":"TG",
    "wof:name":"Kodiokpegble",
    "wof:placetype":"locality"
},
  "geometry": {"coordinates":[1.11667,7.98333],"type":"Point"}
}