{
  "type": "Feature",
  "properties": {
    "gn:admin1_code":"0.0",
    "gn:asciiname":"Langonde",
    "gn:country_code":"TG",
    "gn:dem":320,
    "gn:feature_class":"P",
    "gn:feature_code":"PPL",
    "gn:name":"Langond\u00e9",
    "gn:population":0,
    "gn:timezone":"Africa/Lome",
    "iso:country":"TG",
    "name:ceb_x_preferred":[
        "Langond\u00e9"
    ],
    "name:fra_x_preferred":[
        "Langonde"
    ],
    "name:urd_x_preferred":[
        "\u0644\u0627\u0646\u06af\u0648\u0646\u0688\u06cc"
    ],
    "wof:name":"Langonde",
    "wof:placetype":"locality"
},
  "geometry": {"coordinates":[0.75,9.21667],"type":"Point"}
}