{
  "type": "Feature",
  "properties": {
    "gn:admin1_code":"0.0",
    "gn:asciiname":"Kourientre",
    "gn:country_code":"TG",
    "gn:dem":263,
    "gn:feature_class":"P",
    "gn:feature_code":"PPL",
    "gn:name":"Kourientr\u00e9",
    "gn:population":0,
    "gn:timezone":"Africa/Lome",
    "iso:country":"TG",
    "wof:name":"Kourientre",
    "wof:placetype":"locality"
},
  "geometry": {"coordinates":[0.26667,10.98333],"type":"Point"}
}