{
  "type": "Feature",
  "properties": {
    "gn:admin1_code":"0.0",
    "gn:asciiname":"Foulandi",
    "gn:country_code":"TG",
    "gn:dem":432,
    "gn:feature_class":"P",
    "gn:feature_code":"PPL",
    "gn:name":"Foulandi",
    "gn:population":0,
    "gn:timezone":"Africa/Lome",
    "iso:country":"TG",
    "wof:name":"Foulandi",
    "wof:placetype":"locality"
},
  "geometry": {"coordinates":[1.11667,9.03333],"type":"Point"}
}