{
  "type": "Feature",
  "properties": {
    "gn:admin1_code":"0.0",
    "gn:asciiname":"Kpondave",
    "gn:country_code":"TG",
    "gn:dem":6,
    "gn:feature_class":"P",
    "gn:feature_code":"PPL",
    "gn:name":"Kpondav\u00e9",
    "gn:population":0,
    "gn:timezone":"Africa/Lome",
    "iso:country":"TG",
    "wof:name":"Kpondave",
    "wof:placetype":"locality"
},
  "geometry": {"coordinates":[1.78333,6.36667],"type":"Point"}
}