{
  "type": "Feature",
  "properties": {
    "gn:admin1_code":"0.0",
    "gn:asciiname":"Edji",
    "gn:country_code":"TG",
    "gn:dem":95,
    "gn:feature_class":"P",
    "gn:feature_code":"PPL",
    "gn:name":"Edji",
    "gn:population":0,
    "gn:timezone":"Africa/Lome",
    "iso:country":"TG",
    "wof:name":"Edji",
    "wof:placetype":"locality"
},
  "geometry": {"coordinates":[0.86667,6.38333],"type":"Point"}
}