{
  "type": "Feature",
  "properties": {
    "gn:admin1_code":"0.0",
    "gn:asciiname":"Bafo",
    "gn:cc2":"TG",
    "gn:country_code":"TG",
    "gn:dem":320,
    "gn:feature_class":"P",
    "gn:feature_code":"PPL",
    "gn:name":"Bafo",
    "gn:population":0,
    "gn:timezone":"Africa/Lome",
    "iso:country":"TG",
    "name:und_x_variant":[
        "Bato",
        "Bafo"
    ],
    "wof:name":"Bafo",
    "wof:placetype":"locality"
},
  "geometry": {"coordinates":[0.95,7.81667],"type":"Point"}
}