{
  "type": "Feature",
  "properties": {
    "gn:admin1_code":"0.0",
    "gn:asciiname":"Tokplikope",
    "gn:country_code":"TG",
    "gn:dem":319,
    "gn:feature_class":"P",
    "gn:feature_code":"PPL",
    "gn:name":"Tokplikop\u00e9",
    "gn:population":0,
    "gn:timezone":"Africa/Lome",
    "iso:country":"TG",
    "wof:name":"Tokplikope",
    "wof:placetype":"locality"
},
  "geometry": {"coordinates":[0.83333,7.25],"type":"Point"}
}