{
  "type": "Feature",
  "properties": {
    "gn:admin1_code":"24.0",
    "gn:asciiname":"Komlavi",
    "gn:country_code":"TG",
    "gn:dem":6,
    "gn:feature_class":"P",
    "gn:feature_code":"PPL",
    "gn:name":"Komlavi",
    "gn:population":0,
    "gn:timezone":"Africa/Lome",
    "iso:country":"TG",
    "wof:name":"Komlavi",
    "wof:placetype":"locality"
},
  "geometry": {"coordinates":[1.42139,6.20417],"type":"Point"}
}