{
  "type": "Feature",
  "properties": {
    "gn:admin1_code":"0.0",
    "gn:asciiname":"Kouaketa",
    "gn:country_code":"TG",
    "gn:dem":315,
    "gn:feature_class":"P",
    "gn:feature_code":"PPL",
    "gn:name":"Kouak\u00e9ta",
    "gn:population":0,
    "gn:timezone":"Africa/Lome",
    "iso:country":"TG",
    "wof:name":"Kouaketa",
    "wof:placetype":"locality"
},
  "geometry": {"coordinates":[0.83333,7.05],"type":"Point"}
}