{
  "type": "Feature",
  "properties": {
    "gn:admin1_code":"0.0",
    "gn:asciiname":"Adjakakope",
    "gn:cc2":"TG",
    "gn:country_code":"TG",
    "gn:dem":100,
    "gn:feature_class":"P",
    "gn:feature_code":"PPL",
    "gn:name":"Adjakakop\u00e9",
    "gn:population":0,
    "gn:timezone":"Africa/Lome",
    "iso:country":"TG",
    "name:und_x_variant":[
        "Adzyaka Kop\u00e9",
        "Aziakakop\u00e9",
        "Adjakakop\u00e9"
    ],
    "wof:name":"Adjakakope",
    "wof:placetype":"locality"
},
  "geometry": {"coordinates":[0.95,6.63333],"type":"Point"}
}