{
  "type": "Feature",
  "properties": {
    "gn:admin1_code":"0.0",
    "gn:asciiname":"Bourgue",
    "gn:country_code":"TG",
    "gn:dem":199,
    "gn:feature_class":"P",
    "gn:feature_code":"PPL",
    "gn:name":"Bourgu\u00e9",
    "gn:population":0,
    "gn:timezone":"Africa/Lome",
    "iso:country":"TG",
    "wof:name":"Bourgue",
    "wof:placetype":"locality"
},
  "geometry": {"coordinates":[0.13333,10.55],"type":"Point"}
}