{
  "type": "Feature",
  "properties": {
    "gn:admin1_code":"0.0",
    "gn:asciiname":"Melamboua",
    "gn:cc2":"TG",
    "gn:country_code":"TG",
    "gn:dem":446,
    "gn:feature_class":"P",
    "gn:feature_code":"PPL",
    "gn:name":"M\u00e9lamboua",
    "gn:population":0,
    "gn:timezone":"Africa/Lome",
    "iso:country":"TG",
    "name:und_x_variant":[
        "M\u00e9lanmboua",
        "M\u00e9lamboua"
    ],
    "wof:name":"Melamboua",
    "wof:placetype":"locality"
},
  "geometry": {"coordinates":[0.91667,8.68333],"type":"Point"}
}