{
  "type": "Feature",
  "properties": {
    "gn:admin1_code":"0.0",
    "gn:asciiname":"Siou Kawa",
    "gn:cc2":"TG",
    "gn:country_code":"TG",
    "gn:dem":406,
    "gn:feature_class":"P",
    "gn:feature_code":"PPL",
    "gn:name":"Siou Kawa",
    "gn:population":0,
    "gn:timezone":"Africa/Lome",
    "iso:country":"TG",
    "name:und_x_variant":[
        "Kaoua",
        "Kaua",
        "Siou Kawa"
    ],
    "wof:name":"Siou Kawa",
    "wof:placetype":"locality"
},
  "geometry": {"coordinates":[1.28333,9.71667],"type":"Point"}
}