{
  "type": "Feature",
  "properties": {
    "gn:admin1_code":"0.0",
    "gn:asciiname":"Madiamakou",
    "gn:country_code":"TG",
    "gn:dem":134,
    "gn:feature_class":"P",
    "gn:feature_code":"PPL",
    "gn:name":"Madiamakou",
    "gn:population":0,
    "gn:timezone":"Africa/Lome",
    "iso:country":"TG",
    "wof:name":"Madiamakou",
    "wof:placetype":"locality"
},
  "geometry": {"coordinates":[1.33333,7.23333],"type":"Point"}
}