{
  "type": "Feature",
  "properties": {
    "gn:admin1_code":"26.0",
    "gn:asciiname":"Bidjanga",
    "gn:country_code":"TG",
    "gn:dem":310,
    "gn:feature_class":"P",
    "gn:feature_code":"PPL",
    "gn:name":"Bidjanga",
    "gn:population":0,
    "gn:timezone":"Africa/Lome",
    "iso:country":"TG",
    "name:und_x_variant":[
        "Bidjenga",
        "Bidjanga"
    ],
    "wof:name":"Bidjanga",
    "wof:placetype":"locality"
},
  "geometry": {"coordinates":[0.27083,10.7175],"type":"Point"}
}