{
  "type": "Feature",
  "properties": {
    "gn:admin1_code":"24.0",
    "gn:asciiname":"Togome",
    "gn:country_code":"TG",
    "gn:dem":26,
    "gn:feature_class":"P",
    "gn:feature_code":"PPL",
    "gn:name":"Togom\u00e9",
    "gn:population":0,
    "gn:timezone":"Africa/Lome",
    "iso:country":"TG",
    "wof:name":"Togome",
    "wof:placetype":"locality"
},
  "geometry": {"coordinates":[1.22194,6.22833],"type":"Point"}
}