{
  "type": "Feature",
  "properties": {
    "gn:admin1_code":"0.0",
    "gn:asciiname":"Yakoubokope",
    "gn:cc2":"TG",
    "gn:country_code":"TG",
    "gn:dem":157,
    "gn:feature_class":"P",
    "gn:feature_code":"PPL",
    "gn:name":"Yakoubokop\u00e9",
    "gn:population":0,
    "gn:timezone":"Africa/Lome",
    "iso:country":"TG",
    "name:und_x_variant":[
        "Yacoubokop\u00e9",
        "Yakoubokop\u00e9"
    ],
    "wof:name":"Yakoubokope",
    "wof:placetype":"locality"
},
  "geometry": {"coordinates":[1.15,7.35],"type":"Point"}
}