{
  "type": "Feature",
  "properties": {
    "gn:admin1_code":"0.0",
    "gn:asciiname":"Masseda",
    "gn:cc2":"TG",
    "gn:country_code":"TG",
    "gn:dem":18,
    "gn:feature_class":"P",
    "gn:feature_code":"PPL",
    "gn:name":"Mass\u00e9da",
    "gn:population":0,
    "gn:timezone":"Africa/Lome",
    "iso:country":"TG",
    "name:und_x_variant":[
        "Mas\u00e9da",
        "Mass\u00e9da"
    ],
    "wof:name":"Masseda",
    "wof:placetype":"locality"
},
  "geometry": {"coordinates":[1.68333,6.45],"type":"Point"}
}