{
  "type": "Feature",
  "properties": {
    "gn:admin1_code":"0.0",
    "gn:asciiname":"Dengbaza",
    "gn:country_code":"TG",
    "gn:dem":317,
    "gn:feature_class":"P",
    "gn:feature_code":"PPL",
    "gn:name":"Dengbaza",
    "gn:population":0,
    "gn:timezone":"Africa/Lome",
    "iso:country":"TG",
    "wof:name":"Dengbaza",
    "wof:placetype":"locality"
},
  "geometry": {"coordinates":[0.93333,9.43333],"type":"Point"}
}