{
  "type": "Feature",
  "properties": {
    "gn:admin1_code":"0.0",
    "gn:asciiname":"Kissachieou",
    "gn:country_code":"TG",
    "gn:dem":201,
    "gn:feature_class":"P",
    "gn:feature_code":"PPL",
    "gn:name":"Kissachi\u00e9ou",
    "gn:population":0,
    "gn:timezone":"Africa/Lome",
    "iso:country":"TG",
    "name:und_x_variant":[
        "Kissachi\u00e9ou"
    ],
    "wof:name":"Kissachieou",
    "wof:placetype":"locality"
},
  "geometry": {"coordinates":[0.63333,9.25],"type":"Point"}
}