{
  "type": "Feature",
  "properties": {
    "gn:admin1_code":"0.0",
    "gn:asciiname":"Kpatsougome",
    "gn:cc2":"TG",
    "gn:country_code":"TG",
    "gn:dem":96,
    "gn:feature_class":"P",
    "gn:feature_code":"PPL",
    "gn:name":"Kpatsougom\u00e9",
    "gn:population":0,
    "gn:timezone":"Africa/Lome",
    "iso:country":"TG",
    "name:und_x_variant":[
        "Kpesougom\u00e9",
        "Kpatsougom\u00e9"
    ],
    "wof:name":"Kpatsougome",
    "wof:placetype":"locality"
},
  "geometry": {"coordinates":[0.85,6.46667],"type":"Point"}
}