{
  "type": "Feature",
  "properties": {
    "gn:admin1_code":"24.0",
    "gn:asciiname":"Sanyako",
    "gn:country_code":"TG",
    "gn:dem":49,
    "gn:feature_class":"P",
    "gn:feature_code":"PPL",
    "gn:name":"Sanyako",
    "gn:population":0,
    "gn:timezone":"Africa/Lome",
    "iso:country":"TG",
    "name:und_x_variant":[
        "Sanyanko",
        "Sagnanko",
        "Sanyako"
    ],
    "wof:name":"Sanyako",
    "wof:placetype":"locality"
},
  "geometry": {"coordinates":[1.14,6.24722],"type":"Point"}
}