{
  "type": "Feature",
  "properties": {
    "gn:admin1_code":"0.0",
    "gn:asciiname":"Totoi",
    "gn:country_code":"TG",
    "gn:dem":296,
    "gn:feature_class":"P",
    "gn:feature_code":"PPL",
    "gn:name":"Toto\u00ef",
    "gn:population":0,
    "gn:timezone":"Africa/Lome",
    "iso:country":"TG",
    "wof:name":"Totoi",
    "wof:placetype":"locality"
},
  "geometry": {"coordinates":[1.33333,8.25],"type":"Point"}
}