{
  "type": "Feature",
  "properties": {
    "gn:admin1_code":"0.0",
    "gn:asciiname":"Katcha",
    "gn:country_code":"TG",
    "gn:dem":216,
    "gn:feature_class":"P",
    "gn:feature_code":"PPL",
    "gn:name":"Katcha",
    "gn:population":0,
    "gn:timezone":"Africa/Lome",
    "iso:country":"TG",
    "name:ceb_x_preferred":[
        "Katcha"
    ],
    "name:ita_x_preferred":[
        "Katcha"
    ],
    "name:swe_x_preferred":[
        "Katcha"
    ],
    "wof:name":"Katcha",
    "wof:placetype":"locality"
},
  "geometry": {"coordinates":[0.65,9.28333],"type":"Point"}
}