{
  "type": "Feature",
  "properties": {
    "gn:admin1_code":"0.0",
    "gn:asciiname":"Boungbale",
    "gn:country_code":"TG",
    "gn:dem":163,
    "gn:feature_class":"P",
    "gn:feature_code":"PPL",
    "gn:name":"Boungbal\u00e9",
    "gn:population":0,
    "gn:timezone":"Africa/Lome",
    "iso:country":"TG",
    "wof:name":"Boungbale",
    "wof:placetype":"locality"
},
  "geometry": {"coordinates":[0.66667,9.85],"type":"Point"}
}