{
  "type": "Feature",
  "properties": {
    "gn:admin1_code":"24.0",
    "gn:asciiname":"Agbetchafan",
    "gn:country_code":"TG",
    "gn:dem":40,
    "gn:feature_class":"P",
    "gn:feature_code":"PPL",
    "gn:name":"Agb\u00e9tchafan",
    "gn:population":0,
    "gn:timezone":"Africa/Lome",
    "iso:country":"TG",
    "wof:name":"Agbetchafan",
    "wof:placetype":"locality"
},
  "geometry": {"coordinates":[1.16972,6.22028],"type":"Point"}
}