{
  "type": "Feature",
  "properties": {
    "gn:admin1_code":"24.0",
    "gn:asciiname":"Djamla",
    "gn:country_code":"TG",
    "gn:dem":34,
    "gn:feature_class":"P",
    "gn:feature_code":"PPL",
    "gn:name":"Djamla",
    "gn:population":0,
    "gn:timezone":"Africa/Lome",
    "iso:country":"TG",
    "wof:name":"Djamla",
    "wof:placetype":"locality"
},
  "geometry": {"coordinates":[1.19667,6.20778],"type":"Point"}
}