{
  "type": "Feature",
  "properties": {
    "gn:admin1_code":"0.0",
    "gn:asciiname":"Akouble",
    "gn:country_code":"TG",
    "gn:dem":238,
    "gn:feature_class":"P",
    "gn:feature_code":"PPL",
    "gn:name":"Akoubl\u00e9",
    "gn:population":0,
    "gn:timezone":"Africa/Lome",
    "iso:country":"TG",
    "wof:name":"Akouble",
    "wof:placetype":"locality"
},
  "geometry": {"coordinates":[1.23333,8.11667],"type":"Point"}
}