{
  "type": "Feature",
  "properties": {
    "gn:admin1_code":"0.0",
    "gn:asciiname":"Akponte",
    "gn:country_code":"TG",
    "gn:dem":258,
    "gn:feature_class":"P",
    "gn:feature_code":"PPL",
    "gn:name":"Akpont\u00e8",
    "gn:population":0,
    "gn:timezone":"Africa/Lome",
    "iso:country":"TG",
    "wof:name":"Akponte",
    "wof:placetype":"locality"
},
  "geometry": {"coordinates":[0.95,9.93333],"type":"Point"}
}