{
  "type": "Feature",
  "properties": {
    "gn:admin1_code":"0.0",
    "gn:asciiname":"Afidenigba",
    "gn:country_code":"TG",
    "gn:dem":283,
    "gn:feature_class":"P",
    "gn:feature_code":"PPL",
    "gn:name":"Afid\u00e9nigba",
    "gn:population":0,
    "gn:timezone":"Africa/Lome",
    "iso:country":"TG",
    "wof:name":"Afidenigba",
    "wof:placetype":"locality"
},
  "geometry": {"coordinates":[1.15,7.58333],"type":"Point"}
}