{
  "type": "Feature",
  "properties": {
    "gn:admin1_code":"24.0",
    "gn:asciiname":"Kovie",
    "gn:country_code":"TG",
    "gn:dem":49,
    "gn:feature_class":"P",
    "gn:feature_code":"PPL",
    "gn:name":"Kovi\u00e9",
    "gn:population":0,
    "gn:timezone":"Africa/Lome",
    "iso:country":"TG",
    "name:und_x_variant":[
        "Akovi\u00e9p\u00e9",
        "Kovi\u00e9p\u00e9",
        "Akovy\u00e9p\u00e9",
        "Kovy\u00e9p\u00e9",
        "Kovi\u00e9"
    ],
    "wof:name":"Kovie",
    "wof:placetype":"locality"
},
  "geometry": {"coordinates":[1.11167,6.34222],"type":"Point"}
}