{
  "type": "Feature",
  "properties": {
    "gn:admin1_code":"0.0",
    "gn:asciiname":"Garokope",
    "gn:country_code":"TG",
    "gn:dem":106,
    "gn:feature_class":"P",
    "gn:feature_code":"PPL",
    "gn:name":"Garokop\u00e9",
    "gn:population":0,
    "gn:timezone":"Africa/Lome",
    "iso:country":"TG",
    "wof:name":"Garokope",
    "wof:placetype":"locality"
},
  "geometry": {"coordinates":[0.91667,6.46667],"type":"Point"}
}