{
  "type": "Feature",
  "properties": {
    "gn:admin1_code":"0.0",
    "gn:asciiname":"Batoume",
    "gn:country_code":"TG",
    "gn:dem":147,
    "gn:feature_class":"P",
    "gn:feature_code":"PPL",
    "gn:name":"Batoum\u00e9",
    "gn:population":0,
    "gn:timezone":"Africa/Lome",
    "iso:country":"TG",
    "wof:name":"Batoume",
    "wof:placetype":"locality"
},
  "geometry": {"coordinates":[0.98333,6.88333],"type":"Point"}
}