{
  "type": "Feature",
  "properties": {
    "gn:admin1_code":"0.0",
    "gn:asciiname":"Gboto Eklohome",
    "gn:country_code":"TG",
    "gn:dem":94,
    "gn:feature_class":"P",
    "gn:feature_code":"PPL",
    "gn:name":"Gboto Eklohom\u00e9",
    "gn:population":0,
    "gn:timezone":"Africa/Lome",
    "iso:country":"TG",
    "wof:name":"Gboto Eklohome",
    "wof:placetype":"locality"
},
  "geometry": {"coordinates":[1.51667,6.66667],"type":"Point"}
}