{
  "type": "Feature",
  "properties": {
    "gn:admin1_code":"0.0",
    "gn:asciiname":"Teba",
    "gn:country_code":"TG",
    "gn:dem":168,
    "gn:feature_class":"P",
    "gn:feature_code":"PPL",
    "gn:name":"T\u00e9ba",
    "gn:population":0,
    "gn:timezone":"Africa/Lome",
    "iso:country":"TG",
    "name:ara_x_preferred":[
        "\u062a\u064a\u0628\u0627"
    ],
    "name:cat_x_preferred":[
        "Teba"
    ],
    "name:ceb_x_preferred":[
        "Teba"
    ],
    "name:deu_x_preferred":[
        "Teba"
    ],
    "name:epo_x_preferred":[
        "Teba"
    ],
    "name:eus_x_preferred":[
        "Teba"
    ],
    "name:fra_x_preferred":[
        "Teba"
    ],
    "name:hat_x_preferred":[
        "Teba"
    ],
    "name:hun_x_preferred":[
        "Teba"
    ],
    "name:hye_x_preferred":[
        "\u054f\u0565\u0562\u0561"
    ],
    "name:ind_x_preferred":[
        "Teba"
    ],
    "name:ita_x_preferred":[
        "Teba"
    ],
    "name:kon_x_preferred":[
        "Teba"
    ],
    "name:msa_x_preferred":[
        "Teba"
    ],
    "name:nld_x_preferred":[
        "Teba"
    ],
    "name:oci_x_preferred":[
        "Teba"
    ],
    "name:pol_x_preferred":[
        "Teba"
    ],
    "name:por_x_preferred":[
        "Teba"
    ],
    "name:rus_x_preferred":[
        "\u0422\u0435\u0431\u0430"
    ],
    "name:spa_x_preferred":[
        "Teba"
    ],
    "name:swe_x_preferred":[
        "Teba"
    ],
    "name:ukr_x_preferred":[
        "\u0422\u0435\u0431\u0430"
    ],
    "name:uzb_x_preferred":[
        "Teba"
    ],
    "name:vie_x_preferred":[
        "Teba"
    ],
    "name:war_x_preferred":[
        "Teba"
    ],
    "name:zho_x_preferred":[
        "\u7279\u74e6"
    ],
    "wof:name":"Teba",
    "wof:placetype":"locality"
},
  "geometry": {"coordinates":[1.13333,7.33333],"type":"Point"}
}