{
  "type": "Feature",
  "properties": {
    "gn:admin1_code":"0.0",
    "gn:asciiname":"Teba",
    "gn:country_code":"TG",
    "gn:dem":168,
    "gn:feature_class":"P",
    "gn:feature_code":"PPL",
    "gn:name":"T\u00e9ba",
    "gn:population":0,
    "gn:timezone":"Africa/Lome",
    "iso:country":"TG",
    "wof:name":"Teba",
    "wof:placetype":"locality"
},
  "geometry": {"coordinates":[1.13333,7.33333],"type":"Point"}
}