{
  "type": "Feature",
  "properties": {
    "gn:admin1_code":"0.0",
    "gn:asciiname":"Djakpo Djobedji",
    "gn:cc2":"TG",
    "gn:country_code":"TG",
    "gn:dem":112,
    "gn:feature_class":"P",
    "gn:feature_code":"PPL",
    "gn:name":"Djakpo Djob\u00e9dji",
    "gn:population":0,
    "gn:timezone":"Africa/Lome",
    "iso:country":"TG",
    "name:und_x_variant":[
        "Djakpo",
        "Djakpo Djob\u00e9dji"
    ],
    "wof:name":"Djakpo Djobedji",
    "wof:placetype":"locality"
},
  "geometry": {"coordinates":[1.01667,6.66667],"type":"Point"}
}