{
  "type": "Feature",
  "properties": {
    "gn:admin1_code":"0.0",
    "gn:asciiname":"Ayekpore",
    "gn:country_code":"TG",
    "gn:dem":196,
    "gn:feature_class":"P",
    "gn:feature_code":"PPL",
    "gn:name":"Ay\u00e9kpor\u00e9",
    "gn:population":0,
    "gn:timezone":"Africa/Lome",
    "iso:country":"TG",
    "wof:name":"Ayekpore",
    "wof:placetype":"locality"
},
  "geometry": {"coordinates":[0.63333,10.06667],"type":"Point"}
}