{
  "type": "Feature",
  "properties": {
    "gn:admin1_code":"0.0",
    "gn:asciiname":"Kokoudi",
    "gn:cc2":"TG",
    "gn:country_code":"TG",
    "gn:dem":434,
    "gn:feature_class":"P",
    "gn:feature_code":"PPL",
    "gn:name":"Kokoudi",
    "gn:population":0,
    "gn:timezone":"Africa/Lome",
    "iso:country":"TG",
    "name:und_x_variant":[
        "Kokondi",
        "Kokoudi"
    ],
    "wof:name":"Kokoudi",
    "wof:placetype":"locality"
},
  "geometry": {"coordinates":[1.18333,9.45],"type":"Point"}
}