{
  "type": "Feature",
  "properties": {
    "gn:admin1_code":"0.0",
    "gn:asciiname":"Tounabopi",
    "gn:country_code":"TG",
    "gn:dem":145,
    "gn:feature_class":"P",
    "gn:feature_code":"PPL",
    "gn:name":"Tounabopi",
    "gn:population":0,
    "gn:timezone":"Africa/Lome",
    "iso:country":"TG",
    "wof:name":"Tounabopi",
    "wof:placetype":"locality"
},
  "geometry": {"coordinates":[0.56667,9.86667],"type":"Point"}
}