{
  "type": "Feature",
  "properties": {
    "gn:admin1_code":"24.0",
    "gn:asciiname":"Atidjon",
    "gn:country_code":"TG",
    "gn:dem":38,
    "gn:feature_class":"P",
    "gn:feature_code":"PPL",
    "gn:name":"Atidjon",
    "gn:population":0,
    "gn:timezone":"Africa/Lome",
    "iso:country":"TG",
    "name:und_x_variant":[
        "Atidji",
        "Atidjon"
    ],
    "wof:name":"Atidjon",
    "wof:placetype":"locality"
},
  "geometry": {"coordinates":[1.09833,6.24167],"type":"Point"}
}