{
  "type": "Feature",
  "properties": {
    "gn:admin1_code":"24.0",
    "gn:asciiname":"Akepe Dzogbepime",
    "gn:country_code":"TG",
    "gn:dem":32,
    "gn:feature_class":"P",
    "gn:feature_code":"PPL",
    "gn:name":"Ak\u00e9p\u00e9 Dzogb\u00e9pim\u00e9",
    "gn:population":0,
    "gn:timezone":"Africa/Lome",
    "iso:country":"TG",
    "wof:name":"Akepe Dzogbepime",
    "wof:placetype":"locality"
},
  "geometry": {"coordinates":[1.04972,6.24389],"type":"Point"}
}