{
  "type": "Feature",
  "properties": {
    "gn:admin1_code":"0.0",
    "gn:asciiname":"Betoue",
    "gn:cc2":"TG",
    "gn:country_code":"TG",
    "gn:dem":171,
    "gn:feature_class":"P",
    "gn:feature_code":"PPL",
    "gn:name":"B\u00e9tou\u00e9",
    "gn:population":0,
    "gn:timezone":"Africa/Lome",
    "iso:country":"TG",
    "name:und_x_variant":[
        "B\u00e9lou\u00e9",
        "B\u00e9tou\u00e9"
    ],
    "wof:name":"Betoue",
    "wof:placetype":"locality"
},
  "geometry": {"coordinates":[1.56667,7.38333],"type":"Point"}
}