{
  "type": "Feature",
  "properties": {
    "gn:admin1_code":"0.0",
    "gn:asciiname":"Badja",
    "gn:country_code":"TG",
    "gn:dem":85,
    "gn:feature_class":"P",
    "gn:feature_code":"PPL",
    "gn:name":"Badja",
    "gn:population":0,
    "gn:timezone":"Africa/Lome",
    "iso:country":"TG",
    "name:cat_x_preferred":[
        "Badja"
    ],
    "name:ceb_x_preferred":[
        "Badja"
    ],
    "name:swe_x_preferred":[
        "Badja"
    ],
    "wof:name":"Badja",
    "wof:placetype":"locality"
},
  "geometry": {"coordinates":[0.98333,6.38333],"type":"Point"}
}