{
  "type": "Feature",
  "properties": {
    "gn:admin1_code":"0.0",
    "gn:asciiname":"Sara",
    "gn:country_code":"TG",
    "gn:dem":438,
    "gn:feature_class":"P",
    "gn:feature_code":"PPL",
    "gn:name":"Sara",
    "gn:population":0,
    "gn:timezone":"Africa/Lome",
    "iso:country":"TG",
    "name:ara_x_preferred":[
        "\u0633\u0627\u0631\u0629"
    ],
    "name:aze_x_preferred":[
        "Sara"
    ],
    "name:bel_x_preferred":[
        "\u0421\u0430\u0440\u0430"
    ],
    "name:bul_x_preferred":[
        "\u0421\u0430\u0440\u0430"
    ],
    "name:ceb_x_preferred":[
        "Sara"
    ],
    "name:deu_x_preferred":[
        "Sara"
    ],
    "name:eus_x_preferred":[
        "Sara"
    ],
    "name:fin_x_preferred":[
        "Sara"
    ],
    "name:fra_x_preferred":[
        "Sara"
    ],
    "name:ind_x_preferred":[
        "Sara"
    ],
    "name:ita_x_preferred":[
        "Sara"
    ],
    "name:jpn_x_preferred":[
        "\u30b5\u30e9"
    ],
    "name:kor_x_preferred":[
        "\uc0ac\ub77c"
    ],
    "name:kur_x_preferred":[
        "Sara"
    ],
    "name:lit_x_preferred":[
        "Sara"
    ],
    "name:nld_x_preferred":[
        "Sara"
    ],
    "name:pol_x_preferred":[
        "Sara"
    ],
    "name:por_x_preferred":[
        "Sara"
    ],
    "name:que_x_preferred":[
        "Sara"
    ],
    "name:rus_x_preferred":[
        "\u0421\u0430\u0440\u0430"
    ],
    "name:spa_x_preferred":[
        "Sara"
    ],
    "name:swe_x_preferred":[
        "Sara"
    ],
    "name:tgl_x_preferred":[
        "Sara"
    ],
    "name:tur_x_preferred":[
        "Sara"
    ],
    "name:ukr_x_preferred":[
        "\u0421\u0430\u0440\u0430"
    ],
    "name:war_x_preferred":[
        "Sara"
    ],
    "wof:name":"Sara",
    "wof:placetype":"locality"
},
  "geometry": {"coordinates":[0.81667,9.45],"type":"Point"}
}