{
  "type": "Feature",
  "properties": {
    "gn:admin1_code":"24.0",
    "gn:asciiname":"Agogoudjou",
    "gn:country_code":"TG",
    "gn:dem":7,
    "gn:feature_class":"P",
    "gn:feature_code":"PPL",
    "gn:name":"Agogoudjou",
    "gn:population":0,
    "gn:timezone":"Africa/Lome",
    "iso:country":"TG",
    "wof:name":"Agogoudjou",
    "wof:placetype":"locality"
},
  "geometry": {"coordinates":[1.43056,6.21167],"type":"Point"}
}