{
  "type": "Feature",
  "properties": {
    "gn:admin1_code":"0.0",
    "gn:asciiname":"Amekoussikope",
    "gn:country_code":"TG",
    "gn:dem":232,
    "gn:feature_class":"P",
    "gn:feature_code":"PPL",
    "gn:name":"Am\u00e9koussikop\u00e9",
    "gn:population":0,
    "gn:timezone":"Africa/Lome",
    "iso:country":"TG",
    "wof:name":"Amekoussikope",
    "wof:placetype":"locality"
},
  "geometry": {"coordinates":[0.58333,7.41667],"type":"Point"}
}