{
  "type": "Feature",
  "properties": {
    "gn:admin1_code":"0.0",
    "gn:asciiname":"Boutado",
    "gn:country_code":"TG",
    "gn:dem":251,
    "gn:feature_class":"P",
    "gn:feature_code":"PPL",
    "gn:name":"Boutado",
    "gn:population":0,
    "gn:timezone":"Africa/Lome",
    "iso:country":"TG",
    "wof:name":"Boutado",
    "wof:placetype":"locality"
},
  "geometry": {"coordinates":[0.68333,9.35],"type":"Point"}
}