{
  "type": "Feature",
  "properties": {
    "gn:admin1_code":"0.0",
    "gn:asciiname":"Ikoueteka",
    "gn:cc2":"TG",
    "gn:country_code":"TG",
    "gn:dem":198,
    "gn:feature_class":"P",
    "gn:feature_code":"PPL",
    "gn:name":"Ikou\u00e9t\u00e9ka",
    "gn:population":0,
    "gn:timezone":"Africa/Lome",
    "iso:country":"TG",
    "name:und_x_variant":[
        "Ykou\u00e9t\u00e9ka",
        "Ikou\u00e9t\u00e9ka"
    ],
    "wof:name":"Ikoueteka",
    "wof:placetype":"locality"
},
  "geometry": {"coordinates":[1.15,7.75],"type":"Point"}
}