{
  "type": "Feature",
  "properties": {
    "gn:admin1_code":"0.0",
    "gn:asciiname":"Djegba",
    "gn:cc2":"TG",
    "gn:country_code":"TG",
    "gn:dem":110,
    "gn:feature_class":"P",
    "gn:feature_code":"PPL",
    "gn:name":"Djegba",
    "gn:population":0,
    "gn:timezone":"Africa/Lome",
    "iso:country":"TG",
    "name:und_x_variant":[
        "Diogbakp\u00e9",
        "Djegba"
    ],
    "wof:name":"Djegba",
    "wof:placetype":"locality"
},
  "geometry": {"coordinates":[0.86667,6.46667],"type":"Point"}
}