{
  "type": "Feature",
  "properties": {
    "gn:admin1_code":"0.0",
    "gn:asciiname":"Tiamanga",
    "gn:country_code":"TG",
    "gn:dem":153,
    "gn:feature_class":"P",
    "gn:feature_code":"PPL",
    "gn:name":"Tiamanga",
    "gn:population":0,
    "gn:timezone":"Africa/Lome",
    "iso:country":"TG",
    "wof:name":"Tiamanga",
    "wof:placetype":"locality"
},
  "geometry": {"coordinates":[0.75,10.56667],"type":"Point"}
}