{
  "type": "Feature",
  "properties": {
    "gn:admin1_code":"0.0",
    "gn:asciiname":"Toulounkarga",
    "gn:country_code":"TG",
    "gn:dem":189,
    "gn:feature_class":"P",
    "gn:feature_code":"PPL",
    "gn:name":"Toulounkarga",
    "gn:population":0,
    "gn:timezone":"Africa/Lome",
    "iso:country":"TG",
    "wof:name":"Toulounkarga",
    "wof:placetype":"locality"
},
  "geometry": {"coordinates":[0.46667,10.96667],"type":"Point"}
}