{
  "type": "Feature",
  "properties": {
    "gn:admin1_code":"24.0",
    "gn:asciiname":"Yobo",
    "gn:country_code":"TG",
    "gn:dem":25,
    "gn:feature_class":"P",
    "gn:feature_code":"PPL",
    "gn:name":"Yobo",
    "gn:population":0,
    "gn:timezone":"Africa/Lome",
    "iso:country":"TG",
    "name:und_x_variant":[
        "Iobo",
        "Yobo"
    ],
    "wof:name":"Yobo",
    "wof:placetype":"locality"
},
  "geometry": {"coordinates":[1.32889,6.41278],"type":"Point"}
}