{
  "type": "Feature",
  "properties": {
    "gn:admin1_code":"0.0",
    "gn:asciiname":"Seregbane",
    "gn:country_code":"TG",
    "gn:dem":555,
    "gn:feature_class":"P",
    "gn:feature_code":"PPL",
    "gn:name":"Seregban\u00e9",
    "gn:population":0,
    "gn:timezone":"Africa/Lome",
    "iso:country":"TG",
    "wof:name":"Seregbane",
    "wof:placetype":"locality"
},
  "geometry": {"coordinates":[0.73333,7.86667],"type":"Point"}
}