{
  "type": "Feature",
  "properties": {
    "gn:admin1_code":"0.0",
    "gn:asciiname":"Katambara",
    "gn:cc2":"TG",
    "gn:country_code":"TG",
    "gn:dem":365,
    "gn:feature_class":"P",
    "gn:feature_code":"PPL",
    "gn:name":"Katambara",
    "gn:population":0,
    "gn:timezone":"Africa/Lome",
    "iso:country":"TG",
    "name:und_x_variant":[
        "Katammbara",
        "Katambara"
    ],
    "wof:name":"Katambara",
    "wof:placetype":"locality"
},
  "geometry": {"coordinates":[1.16667,8.95],"type":"Point"}
}