{
  "type": "Feature",
  "properties": {
    "gn:admin1_code":"0.0",
    "gn:asciiname":"Baounda",
    "gn:country_code":"TG",
    "gn:dem":464,
    "gn:feature_class":"P",
    "gn:feature_code":"PPL",
    "gn:name":"Baounda",
    "gn:population":0,
    "gn:timezone":"Africa/Lome",
    "iso:country":"TG",
    "wof:name":"Baounda",
    "wof:placetype":"locality"
},
  "geometry": {"coordinates":[1.25,9.03333],"type":"Point"}
}