{
  "type": "Feature",
  "properties": {
    "gn:admin1_code":"0.0",
    "gn:asciiname":"Atikpai",
    "gn:cc2":"TG",
    "gn:country_code":"TG",
    "gn:dem":273,
    "gn:feature_class":"P",
    "gn:feature_code":"PPL",
    "gn:name":"Atikpa\u00ef",
    "gn:population":0,
    "gn:timezone":"Africa/Lome",
    "iso:country":"TG",
    "name:und_x_variant":[
        "Atikpay",
        "Atitpaye",
        "Atikpa\u00ef"
    ],
    "wof:name":"Atikpai",
    "wof:placetype":"locality"
},
  "geometry": {"coordinates":[1.31667,8.18333],"type":"Point"}
}