{
  "type": "Feature",
  "properties": {
    "gn:admin1_code":"0.0",
    "gn:asciiname":"Nyitoe-Zoukpe",
    "gn:cc2":"TG",
    "gn:country_code":"TG",
    "gn:dem":107,
    "gn:feature_class":"P",
    "gn:feature_code":"PPL",
    "gn:name":"Nyito\u00e9-Zoukp\u00e9",
    "gn:population":0,
    "gn:timezone":"Africa/Lome",
    "iso:country":"TG",
    "name:und_x_variant":[
        "Nitou\u00e9",
        "Nyito\u00e9",
        "Zoukp\u00e9",
        "Nyite",
        "Njito\u00e9",
        "Nyito\u00e9-Zoukp\u00e9"
    ],
    "wof:name":"Nyitoe-Zoukpe",
    "wof:placetype":"locality"
},
  "geometry": {"coordinates":[0.65,6.66667],"type":"Point"}
}