{
  "type": "Feature",
  "properties": {
    "gn:admin1_code":"0.0",
    "gn:asciiname":"Obi",
    "gn:country_code":"TG",
    "gn:dem":180,
    "gn:feature_class":"P",
    "gn:feature_code":"PPL",
    "gn:name":"Obi",
    "gn:population":0,
    "gn:timezone":"Africa/Lome",
    "iso:country":"TG",
    "name:ara_x_preferred":[
        "\u0623\u0648\u0628\u064a"
    ],
    "name:ceb_x_preferred":[
        "Obi"
    ],
    "name:ces_x_preferred":[
        "Obi"
    ],
    "name:deu_x_preferred":[
        "Obi"
    ],
    "name:fra_x_preferred":[
        "Obi"
    ],
    "name:hun_x_preferred":[
        "Obi"
    ],
    "name:ind_x_preferred":[
        "Obi"
    ],
    "name:nld_x_preferred":[
        "Obi"
    ],
    "name:pnb_x_preferred":[
        "\u0627\u0648\u0628\u06cc"
    ],
    "name:pol_x_preferred":[
        "Obi"
    ],
    "name:por_x_preferred":[
        "Obi"
    ],
    "name:rus_x_preferred":[
        "\u041e\u0431\u0438"
    ],
    "name:slk_x_preferred":[
        "Obi"
    ],
    "name:spa_x_preferred":[
        "Obi"
    ],
    "name:swe_x_preferred":[
        "Obi"
    ],
    "name:tur_x_preferred":[
        "Obi"
    ],
    "name:ukr_x_preferred":[
        "\u041e\u0431\u0456"
    ],
    "wof:name":"Obi",
    "wof:placetype":"locality"
},
  "geometry": {"coordinates":[1.16667,7.43333],"type":"Point"}
}