{
  "type": "Feature",
  "properties": {
    "gn:admin1_code":"0.0",
    "gn:asciiname":"Kablekope",
    "gn:country_code":"TG",
    "gn:dem":166,
    "gn:feature_class":"P",
    "gn:feature_code":"PPL",
    "gn:name":"Kabl\u00e9kop\u00e9",
    "gn:population":0,
    "gn:timezone":"Africa/Lome",
    "iso:country":"TG",
    "wof:name":"Kablekope",
    "wof:placetype":"locality"
},
  "geometry": {"coordinates":[1.15,7.15],"type":"Point"}
}