{
  "type": "Feature",
  "properties": {
    "gn:admin1_code":"0.0",
    "gn:asciiname":"Broda",
    "gn:country_code":"TG",
    "gn:dem":546,
    "gn:feature_class":"P",
    "gn:feature_code":"PPL",
    "gn:name":"Broda",
    "gn:population":0,
    "gn:timezone":"Africa/Lome",
    "iso:country":"TG",
    "name:ces_x_preferred":[
        "Broda"
    ],
    "name:deu_x_preferred":[
        "Broda"
    ],
    "name:fra_x_preferred":[
        "Broda"
    ],
    "name:heb_x_preferred":[
        "\u05d1\u05e8\u05d5\u05d9\u05d3\u05d0"
    ],
    "name:pol_x_preferred":[
        "Broda"
    ],
    "name:rus_x_preferred":[
        "\u0411\u0440\u043e\u0434\u0430"
    ],
    "wof:name":"Broda",
    "wof:placetype":"locality"
},
  "geometry": {"coordinates":[0.76667,7.83333],"type":"Point"}
}