{
  "type": "Feature",
  "properties": {
    "gn:admin1_code":"0.0",
    "gn:asciiname":"Sogbohoe",
    "gn:country_code":"TG",
    "gn:dem":143,
    "gn:feature_class":"P",
    "gn:feature_code":"PPL",
    "gn:name":"Sogboho\u00e9",
    "gn:population":0,
    "gn:timezone":"Africa/Lome",
    "iso:country":"TG",
    "wof:name":"Sogbohoe",
    "wof:placetype":"locality"
},
  "geometry": {"coordinates":[1.56667,7.28333],"type":"Point"}
}