{
  "type": "Feature",
  "properties": {
    "gn:admin1_code":"0.0",
    "gn:asciiname":"Bountourouga",
    "gn:country_code":"TG",
    "gn:dem":158,
    "gn:feature_class":"P",
    "gn:feature_code":"PPL",
    "gn:name":"Bountourouga",
    "gn:population":0,
    "gn:timezone":"Africa/Lome",
    "iso:country":"TG",
    "wof:name":"Bountourouga",
    "wof:placetype":"locality"
},
  "geometry": {"coordinates":[0.63333,10.25],"type":"Point"}
}