{
  "type": "Feature",
  "properties": {
    "gn:admin1_code":"0.0",
    "gn:asciiname":"Pitambade",
    "gn:cc2":"TG",
    "gn:country_code":"TG",
    "gn:dem":270,
    "gn:feature_class":"P",
    "gn:feature_code":"PPL",
    "gn:name":"Pitambad\u00e9",
    "gn:population":0,
    "gn:timezone":"Africa/Lome",
    "iso:country":"TG",
    "name:und_x_variant":[
        "Pitammbad\u00e9",
        "Pitambad\u00e9"
    ],
    "wof:name":"Pitambade",
    "wof:placetype":"locality"
},
  "geometry": {"coordinates":[0.91667,9.51667],"type":"Point"}
}