{
  "type": "Feature",
  "properties": {
    "gn:admin1_code":"0.0",
    "gn:asciiname":"Djapake",
    "gn:country_code":"TG",
    "gn:dem":432,
    "gn:feature_class":"P",
    "gn:feature_code":"PPL",
    "gn:name":"Djapak\u00e9",
    "gn:population":0,
    "gn:timezone":"Africa/Lome",
    "iso:country":"TG",
    "wof:name":"Djapake",
    "wof:placetype":"locality"
},
  "geometry": {"coordinates":[0.15,10.66667],"type":"Point"}
}