{
  "type": "Feature",
  "properties": {
    "gn:admin1_code":"24.0",
    "gn:asciiname":"Animaoio",
    "gn:country_code":"TG",
    "gn:dem":12,
    "gn:feature_class":"P",
    "gn:feature_code":"PPL",
    "gn:name":"Animaoio",
    "gn:population":0,
    "gn:timezone":"Africa/Lome",
    "iso:country":"TG",
    "name:und_x_variant":[
        "Animabio",
        "Animaoio"
    ],
    "wof:name":"Animaoio",
    "wof:placetype":"locality"
},
  "geometry": {"coordinates":[1.41444,6.43],"type":"Point"}
}