{
  "type": "Feature",
  "properties": {
    "gn:admin1_code":"0.0",
    "gn:asciiname":"Game",
    "gn:country_code":"TG",
    "gn:dem":301,
    "gn:feature_class":"P",
    "gn:feature_code":"PPL",
    "gn:name":"Gam\u00e9",
    "gn:population":0,
    "gn:timezone":"Africa/Lome",
    "iso:country":"TG",
    "wof:name":"Game",
    "wof:placetype":"locality"
},
  "geometry": {"coordinates":[1.06667,7.73333],"type":"Point"}
}