{
  "type": "Feature",
  "properties": {
    "gn:admin1_code":"0.0",
    "gn:asciiname":"Skapatei",
    "gn:country_code":"TG",
    "gn:dem":324,
    "gn:feature_class":"P",
    "gn:feature_code":"PPL",
    "gn:name":"Skapat\u00e9\u00ef",
    "gn:population":0,
    "gn:timezone":"Africa/Lome",
    "iso:country":"TG",
    "wof:name":"Skapatei",
    "wof:placetype":"locality"
},
  "geometry": {"coordinates":[1.08333,9.08333],"type":"Point"}
}