{
  "type": "Feature",
  "properties": {
    "gn:admin1_code":"0.0",
    "gn:asciiname":"Adjakpodji",
    "gn:cc2":"TG",
    "gn:country_code":"TG",
    "gn:dem":516,
    "gn:feature_class":"P",
    "gn:feature_code":"PPL",
    "gn:name":"Adjakpodji",
    "gn:population":0,
    "gn:timezone":"Africa/Lome",
    "iso:country":"TG",
    "name:und_x_variant":[
        "Djabodji",
        "Adjakpodji"
    ],
    "wof:name":"Adjakpodji",
    "wof:placetype":"locality"
},
  "geometry": {"coordinates":[0.81667,7.76667],"type":"Point"}
}