{
  "type": "Feature",
  "properties": {
    "gn:admin1_code":"0.0",
    "gn:asciiname":"Akoda",
    "gn:country_code":"TG",
    "gn:dem":14,
    "gn:feature_class":"P",
    "gn:feature_code":"PPL",
    "gn:name":"Akoda",
    "gn:population":0,
    "gn:timezone":"Africa/Lome",
    "iso:country":"TG",
    "wof:name":"Akoda",
    "wof:placetype":"locality"
},
  "geometry": {"coordinates":[1.55,6.25],"type":"Point"}
}