{
  "type": "Feature",
  "properties": {
    "gn:admin1_code":"0.0",
    "gn:asciiname":"Akoda",
    "gn:country_code":"TG",
    "gn:dem":14,
    "gn:feature_class":"P",
    "gn:feature_code":"PPL",
    "gn:name":"Akoda",
    "gn:population":0,
    "gn:timezone":"Africa/Lome",
    "iso:country":"TG",
    "name:fas_x_preferred":[
        "\u0627\u06a9\u0648\u062f\u0627"
    ],
    "name:ita_x_preferred":[
        "Akoda"
    ],
    "name:min_x_preferred":[
        "Akoda"
    ],
    "name:msa_x_preferred":[
        "Akoda"
    ],
    "name:new_x_preferred":[
        "\u0905\u0915\u094b\u0926\u093e"
    ],
    "name:nld_x_preferred":[
        "Akoda"
    ],
    "name:por_x_preferred":[
        "Akoda"
    ],
    "name:spa_x_preferred":[
        "Akoda"
    ],
    "name:vie_x_preferred":[
        "Akoda"
    ],
    "name:zho_x_preferred":[
        "\u963f\u79d1\u8fbe"
    ],
    "wof:name":"Akoda",
    "wof:placetype":"locality"
},
  "geometry": {"coordinates":[1.55,6.25],"type":"Point"}
}