{
  "type": "Feature",
  "properties": {
    "gn:admin1_code":"24.0",
    "gn:asciiname":"Dose",
    "gn:country_code":"TG",
    "gn:dem":43,
    "gn:feature_class":"P",
    "gn:feature_code":"PPL",
    "gn:name":"Dos\u00e9",
    "gn:population":0,
    "gn:timezone":"Africa/Lome",
    "iso:country":"TG",
    "name:ceb_x_preferred":[
        "Dose"
    ],
    "name:deu_x_preferred":[
        "Dose"
    ],
    "name:fas_x_preferred":[
        "\u062f\u0648\u0632"
    ],
    "name:fra_x_preferred":[
        "Dose"
    ],
    "name:hun_x_preferred":[
        "D\u00f3zis"
    ],
    "name:ita_x_preferred":[
        "Dose"
    ],
    "name:jpn_x_preferred":[
        "\u30c9\u30fc\u30b9"
    ],
    "name:nld_x_preferred":[
        "Dose"
    ],
    "name:rus_x_preferred":[
        "\u0414\u043e\u0437\u0430"
    ],
    "name:swe_x_preferred":[
        "Dose"
    ],
    "name:uzb_x_preferred":[
        "Doza"
    ],
    "wof:name":"Dose",
    "wof:placetype":"locality"
},
  "geometry": {"coordinates":[1.14861,6.23583],"type":"Point"}
}