{
  "type": "Feature",
  "properties": {
    "gn:admin1_code":"0.0",
    "gn:asciiname":"Naboulgou",
    "gn:cc2":"TG",
    "gn:country_code":"TG",
    "gn:dem":158,
    "gn:feature_class":"P",
    "gn:feature_code":"PPL",
    "gn:name":"Naboulgou",
    "gn:population":0,
    "gn:timezone":"Africa/Lome",
    "iso:country":"TG",
    "name:und_x_variant":[
        "Nabulgu",
        "Naboulgou"
    ],
    "wof:name":"Naboulgou",
    "wof:placetype":"locality"
},
  "geometry": {"coordinates":[0.81667,10.15],"type":"Point"}
}