{
  "type": "Feature",
  "properties": {
    "gn:admin1_code":"0.0",
    "gn:asciiname":"Tokpo",
    "gn:country_code":"TG",
    "gn:dem":122,
    "gn:feature_class":"P",
    "gn:feature_code":"PPL",
    "gn:name":"Tokpo",
    "gn:population":0,
    "gn:timezone":"Africa/Lome",
    "iso:country":"TG",
    "wof:name":"Tokpo",
    "wof:placetype":"locality"
},
  "geometry": {"coordinates":[0.91667,6.78333],"type":"Point"}
}