{
  "type": "Feature",
  "properties": {
    "gn:admin1_code":"0.0",
    "gn:asciiname":"Gboto Koissidame",
    "gn:cc2":"TG",
    "gn:country_code":"TG",
    "gn:dem":90,
    "gn:feature_class":"P",
    "gn:feature_code":"PPL",
    "gn:name":"Gboto Koissidam\u00e9",
    "gn:population":0,
    "gn:timezone":"Africa/Lome",
    "iso:country":"TG",
    "name:und_x_variant":[
        "Gboto Koisidam\u00e9",
        "Gboto Koissidam\u00e9"
    ],
    "wof:name":"Gboto Koissidame",
    "wof:placetype":"locality"
},
  "geometry": {"coordinates":[1.48333,6.68333],"type":"Point"}
}