{
  "type": "Feature",
  "properties": {
    "gn:admin1_code":"0.0",
    "gn:asciiname":"Natigou",
    "gn:country_code":"TG",
    "gn:dem":281,
    "gn:feature_class":"P",
    "gn:feature_code":"PPL",
    "gn:name":"Natigou",
    "gn:population":0,
    "gn:timezone":"Africa/Lome",
    "iso:country":"TG",
    "wof:name":"Natigou",
    "wof:placetype":"locality"
},
  "geometry": {"coordinates":[0.28333,10.96667],"type":"Point"}
}