{
  "type": "Feature",
  "properties": {
    "gn:admin1_code":"0.0",
    "gn:asciiname":"Daboute",
    "gn:country_code":"TG",
    "gn:dem":234,
    "gn:feature_class":"P",
    "gn:feature_code":"PPL",
    "gn:name":"Dabout\u00e9",
    "gn:population":0,
    "gn:timezone":"Africa/Lome",
    "iso:country":"TG",
    "name:und_x_variant":[
        "Dabout\u00e9"
    ],
    "wof:name":"Daboute",
    "wof:placetype":"locality"
},
  "geometry": {"coordinates":[0.73333,9.56667],"type":"Point"}
}