{
  "type": "Feature",
  "properties": {
    "gn:admin1_code":"0.0",
    "gn:asciiname":"Naloague",
    "gn:country_code":"TG",
    "gn:dem":269,
    "gn:feature_class":"P",
    "gn:feature_code":"PPL",
    "gn:name":"Naloague",
    "gn:population":0,
    "gn:timezone":"Africa/Lome",
    "iso:country":"TG",
    "wof:name":"Naloague",
    "wof:placetype":"locality"
},
  "geometry": {"coordinates":[0.25,10.76667],"type":"Point"}
}