{
  "type": "Feature",
  "properties": {
    "gn:admin1_code":"24.0",
    "gn:asciiname":"Nomanyo",
    "gn:country_code":"TG",
    "gn:dem":47,
    "gn:feature_class":"P",
    "gn:feature_code":"PPL",
    "gn:name":"Nomanyo",
    "gn:population":0,
    "gn:timezone":"Africa/Lome",
    "iso:country":"TG",
    "wof:name":"Nomanyo",
    "wof:placetype":"locality"
},
  "geometry": {"coordinates":[1.085,6.24528],"type":"Point"}
}