{
  "type": "Feature",
  "properties": {
    "gn:admin1_code":"0.0",
    "gn:asciiname":"Atchoukpe",
    "gn:country_code":"TG",
    "gn:dem":138,
    "gn:feature_class":"P",
    "gn:feature_code":"PPL",
    "gn:name":"Atchoukp\u00e9",
    "gn:population":0,
    "gn:timezone":"Africa/Lome",
    "iso:country":"TG",
    "wof:name":"Atchoukpe",
    "wof:placetype":"locality"
},
  "geometry": {"coordinates":[1.35,6.93333],"type":"Point"}
}