{
  "type": "Feature",
  "properties": {
    "gn:admin1_code":"0.0",
    "gn:asciiname":"Vakpo",
    "gn:cc2":"TG",
    "gn:country_code":"TG",
    "gn:dem":90,
    "gn:feature_class":"P",
    "gn:feature_code":"PPL",
    "gn:name":"Vakpo",
    "gn:population":0,
    "gn:timezone":"Africa/Lome",
    "iso:country":"TG",
    "name:und_x_variant":[
        "Ouakpo",
        "Vakpo"
    ],
    "wof:name":"Vakpo",
    "wof:placetype":"locality"
},
  "geometry": {"coordinates":[0.76667,6.55],"type":"Point"}
}