{
  "type": "Feature",
  "properties": {
    "gn:admin1_code":"0.0",
    "gn:asciiname":"Adjakpohoue",
    "gn:country_code":"TG",
    "gn:dem":168,
    "gn:feature_class":"P",
    "gn:feature_code":"PPL",
    "gn:name":"Adjakpohou\u00e9",
    "gn:population":0,
    "gn:timezone":"Africa/Lome",
    "iso:country":"TG",
    "wof:name":"Adjakpohoue",
    "wof:placetype":"locality"
},
  "geometry": {"coordinates":[1.46667,7.01667],"type":"Point"}
}