{
  "type": "Feature",
  "properties": {
    "gn:admin1_code":"0.0",
    "gn:asciiname":"Didyoyeri",
    "gn:cc2":"TG",
    "gn:country_code":"TG",
    "gn:dem":198,
    "gn:feature_class":"P",
    "gn:feature_code":"PPL",
    "gn:name":"Didyoy\u00e9ri",
    "gn:population":0,
    "gn:timezone":"Africa/Lome",
    "iso:country":"TG",
    "name:und_x_variant":[
        "Dijioyeri",
        "Didyoy\u00e9ri"
    ],
    "wof:name":"Didyoyeri",
    "wof:placetype":"locality"
},
  "geometry": {"coordinates":[0.65,9.31667],"type":"Point"}
}