{
  "type": "Feature",
  "properties": {
    "gn:admin1_code":"24.0",
    "gn:asciiname":"Have",
    "gn:country_code":"TG",
    "gn:dem":68,
    "gn:feature_class":"P",
    "gn:feature_code":"PPL",
    "gn:name":"Hav\u00e9",
    "gn:population":0,
    "gn:timezone":"Africa/Lome",
    "iso:country":"TG",
    "name:und_x_variant":[
        "Hav\u00e9 Kop\u00e9",
        "Hav\u00e9"
    ],
    "wof:name":"Have",
    "wof:placetype":"locality"
},
  "geometry": {"coordinates":[1.25167,6.49389],"type":"Point"}
}