{
  "type": "Feature",
  "properties": {
    "gn:admin1_code":"24.0",
    "gn:asciiname":"Adjivon",
    "gn:country_code":"TG",
    "gn:dem":33,
    "gn:feature_class":"P",
    "gn:feature_code":"PPL",
    "gn:name":"Adjivon",
    "gn:population":0,
    "gn:timezone":"Africa/Lome",
    "iso:country":"TG",
    "wof:name":"Adjivon",
    "wof:placetype":"locality"
},
  "geometry": {"coordinates":[1.14806,6.18917],"type":"Point"}
}