{
  "type": "Feature",
  "properties": {
    "gn:admin1_code":"24.0",
    "gn:asciiname":"Ladjekpo",
    "gn:country_code":"TG",
    "gn:dem":4,
    "gn:feature_class":"P",
    "gn:feature_code":"PPL",
    "gn:name":"Ladj\u00e9kpo",
    "gn:population":0,
    "gn:timezone":"Africa/Lome",
    "iso:country":"TG",
    "wof:name":"Ladjekpo",
    "wof:placetype":"locality"
},
  "geometry": {"coordinates":[1.28056,6.14611],"type":"Point"}
}