{
  "type": "Feature",
  "properties": {
    "gn:admin1_code":"0.0",
    "gn:asciiname":"Expounoume",
    "gn:country_code":"TG",
    "gn:dem":359,
    "gn:feature_class":"P",
    "gn:feature_code":"PPL",
    "gn:name":"Expounoum\u00e9",
    "gn:population":0,
    "gn:timezone":"Africa/Lome",
    "iso:country":"TG",
    "wof:name":"Expounoume",
    "wof:placetype":"locality"
},
  "geometry": {"coordinates":[1.01667,7.55],"type":"Point"}
}