{
  "type": "Feature",
  "properties": {
    "gn:admin1_code":"0.0",
    "gn:asciiname":"Bongbon",
    "gn:country_code":"TG",
    "gn:dem":167,
    "gn:feature_class":"P",
    "gn:feature_code":"PPL",
    "gn:name":"Bongbon",
    "gn:population":0,
    "gn:timezone":"Africa/Lome",
    "iso:country":"TG",
    "wof:name":"Bongbon",
    "wof:placetype":"locality"
},
  "geometry": {"coordinates":[0.65,9.86667],"type":"Point"}
}