{
  "type": "Feature",
  "properties": {
    "gn:admin1_code":"24.0",
    "gn:asciiname":"Valakope",
    "gn:country_code":"TG",
    "gn:dem":29,
    "gn:feature_class":"P",
    "gn:feature_code":"PPL",
    "gn:name":"Valakop\u00e9",
    "gn:population":0,
    "gn:timezone":"Africa/Lome",
    "iso:country":"TG",
    "name:und_x_variant":[
        "Valokop\u00e9",
        "Valakop\u00e9"
    ],
    "wof:name":"Valakope",
    "wof:placetype":"locality"
},
  "geometry": {"coordinates":[1.13083,6.37444],"type":"Point"}
}