{
  "type": "Feature",
  "properties": {
    "gn:admin1_code":"0.0",
    "gn:asciiname":"Wania",
    "gn:country_code":"TG",
    "gn:dem":252,
    "gn:feature_class":"P",
    "gn:feature_code":"PPL",
    "gn:name":"Wania",
    "gn:population":0,
    "gn:timezone":"Africa/Lome",
    "iso:country":"TG",
    "wof:name":"Wania",
    "wof:placetype":"locality"
},
  "geometry": {"coordinates":[0.05,10.95],"type":"Point"}
}