{
  "type": "Feature",
  "properties": {
    "gn:admin1_code":"0.0",
    "gn:asciiname":"Kpedome",
    "gn:cc2":"TG",
    "gn:country_code":"TG",
    "gn:dem":95,
    "gn:feature_class":"P",
    "gn:feature_code":"PPL",
    "gn:name":"Kp\u00e9dom\u00e9",
    "gn:population":0,
    "gn:timezone":"Africa/Lome",
    "iso:country":"TG",
    "name:und_x_variant":[
        "P\u00e9dom\u00e9",
        "Kp\u00e9dom\u00e9"
    ],
    "wof:name":"Kpedome",
    "wof:placetype":"locality"
},
  "geometry": {"coordinates":[0.98333,6.65],"type":"Point"}
}