{
  "type": "Feature",
  "properties": {
    "gn:admin1_code":"0.0",
    "gn:asciiname":"Pamboa",
    "gn:cc2":"TG",
    "gn:country_code":"TG",
    "gn:dem":204,
    "gn:feature_class":"P",
    "gn:feature_code":"PPL",
    "gn:name":"Pamboa",
    "gn:population":0,
    "gn:timezone":"Africa/Lome",
    "iso:country":"TG",
    "name:und_x_variant":[
        "Pammboa",
        "Pamboa"
    ],
    "wof:name":"Pamboa",
    "wof:placetype":"locality"
},
  "geometry": {"coordinates":[0.63333,9.75],"type":"Point"}
}