{
  "type": "Feature",
  "properties": {
    "gn:admin1_code":"0.0",
    "gn:asciiname":"Tchabe",
    "gn:country_code":"TG",
    "gn:dem":226,
    "gn:feature_class":"P",
    "gn:feature_code":"PPL",
    "gn:name":"Tchab\u00e9",
    "gn:population":0,
    "gn:timezone":"Africa/Lome",
    "iso:country":"TG",
    "wof:name":"Tchabe",
    "wof:placetype":"locality"
},
  "geometry": {"coordinates":[1.61667,7.76667],"type":"Point"}
}