{
  "type": "Feature",
  "properties": {
    "gn:admin1_code":"0.0",
    "gn:asciiname":"Konagoui",
    "gn:country_code":"TG",
    "gn:dem":173,
    "gn:feature_class":"P",
    "gn:feature_code":"PPL",
    "gn:name":"Konagoui",
    "gn:population":0,
    "gn:timezone":"Africa/Lome",
    "iso:country":"TG",
    "wof:name":"Konagoui",
    "wof:placetype":"locality"
},
  "geometry": {"coordinates":[1.26667,7.45],"type":"Point"}
}