{
  "type": "Feature",
  "properties": {
    "gn:admin1_code":"0.0",
    "gn:asciiname":"Garimbomb",
    "gn:cc2":"TG",
    "gn:country_code":"TG",
    "gn:dem":183,
    "gn:feature_class":"P",
    "gn:feature_code":"PPL",
    "gn:name":"Garimbomb",
    "gn:population":0,
    "gn:timezone":"Africa/Lome",
    "iso:country":"TG",
    "name:und_x_variant":[
        "Garimmbommb",
        "Garimbommb",
        "Garimbomb"
    ],
    "wof:name":"Garimbomb",
    "wof:placetype":"locality"
},
  "geometry": {"coordinates":[0.75,9.73333],"type":"Point"}
}