{
  "type": "Feature",
  "properties": {
    "gn:admin1_code":"24.0",
    "gn:asciiname":"Pakli Kope",
    "gn:country_code":"TG",
    "gn:dem":37,
    "gn:feature_class":"P",
    "gn:feature_code":"PPL",
    "gn:name":"Pakli Kop\u00e9",
    "gn:population":0,
    "gn:timezone":"Africa/Lome",
    "iso:country":"TG",
    "name:und_x_variant":[
        "D\u00e9ponou",
        "Pakli Kop\u00e9"
    ],
    "wof:name":"Pakli Kope",
    "wof:placetype":"locality"
},
  "geometry": {"coordinates":[1.10611,6.38417],"type":"Point"}
}