{
  "type": "Feature",
  "properties": {
    "gn:admin1_code":"24.0",
    "gn:asciiname":"Dzoubeto",
    "gn:country_code":"TG",
    "gn:dem":72,
    "gn:feature_class":"P",
    "gn:feature_code":"PPL",
    "gn:name":"Dzoub\u00e9to",
    "gn:population":0,
    "gn:timezone":"Africa/Lome",
    "iso:country":"TG",
    "wof:name":"Dzoubeto",
    "wof:placetype":"locality"
},
  "geometry": {"coordinates":[1.06,6.34444],"type":"Point"}
}