{
  "type": "Feature",
  "properties": {
    "gn:admin1_code":"26.0",
    "gn:asciiname":"Koundjoare",
    "gn:country_code":"TG",
    "gn:dem":200,
    "gn:feature_class":"P",
    "gn:feature_code":"PPL",
    "gn:name":"Koundjoar\u00e9",
    "gn:population":0,
    "gn:timezone":"Africa/Lome",
    "iso:country":"TG",
    "name:und_x_variant":[
        "Kondjeare",
        "Koundjouar\u00e9",
        "Kundjore",
        "Pelel\u00e9",
        "Koudjouare",
        "Kandjouar\u00e9",
        "Kondju\u0101re",
        "Koundjoar\u00e9"
    ],
    "wof:name":"Koundjoare",
    "wof:placetype":"locality"
},
  "geometry": {"coordinates":[0.64139,10.94306],"type":"Point"}
}