{
  "type": "Feature",
  "properties": {
    "gn:admin1_code":"0.0",
    "gn:asciiname":"Djeta",
    "gn:cc2":"TG",
    "gn:country_code":"TG",
    "gn:dem":5,
    "gn:feature_class":"P",
    "gn:feature_code":"PPL",
    "gn:name":"Dj\u00e9ta",
    "gn:population":0,
    "gn:timezone":"Africa/Lome",
    "iso:country":"TG",
    "name:und_x_variant":[
        "Jeta",
        "Dj\u00e9ta"
    ],
    "wof:name":"Djeta",
    "wof:placetype":"locality"
},
  "geometry": {"coordinates":[1.75,6.26667],"type":"Point"}
}