{
  "type": "Feature",
  "properties": {
    "gn:admin1_code":"0.0",
    "gn:asciiname":"Agarade",
    "gn:country_code":"TG",
    "gn:dem":743,
    "gn:feature_class":"P",
    "gn:feature_code":"PPL",
    "gn:name":"Agarad\u00e9",
    "gn:population":0,
    "gn:timezone":"Africa/Lome",
    "iso:country":"TG",
    "name:und_x_variant":[
        "Agarad\u00e9"
    ],
    "wof:name":"Agarade",
    "wof:placetype":"locality"
},
  "geometry": {"coordinates":[1.21667,9.28333],"type":"Point"}
}