{
  "type": "Feature",
  "properties": {
    "gn:admin1_code":"0.0",
    "gn:asciiname":"Ponio",
    "gn:country_code":"TG",
    "gn:dem":190,
    "gn:feature_class":"P",
    "gn:feature_code":"PPL",
    "gn:name":"Ponio",
    "gn:population":0,
    "gn:timezone":"Africa/Lome",
    "iso:country":"TG",
    "wof:name":"Ponio",
    "wof:placetype":"locality"
},
  "geometry": {"coordinates":[0.46667,10.58333],"type":"Point"}
}