{
  "type": "Feature",
  "properties": {
    "gn:admin1_code":"23.0",
    "gn:asciiname":"Solla",
    "gn:country_code":"TG",
    "gn:dem":420,
    "gn:feature_class":"P",
    "gn:feature_code":"PPL",
    "gn:name":"Solla",
    "gn:population":0,
    "gn:timezone":"Africa/Lome",
    "iso:country":"TG",
    "name:und_x_variant":[
        "Sola",
        "Solla"
    ],
    "wof:name":"Solla",
    "wof:placetype":"locality"
},
  "geometry": {"coordinates":[1.34889,9.89056],"type":"Point"}
}