{
  "type": "Feature",
  "properties": {
    "gn:admin1_code":"24.0",
    "gn:asciiname":"Kodjo",
    "gn:country_code":"TG",
    "gn:dem":46,
    "gn:feature_class":"P",
    "gn:feature_code":"PPL",
    "gn:name":"Kodjo",
    "gn:population":0,
    "gn:timezone":"Africa/Lome",
    "iso:country":"TG",
    "wof:name":"Kodjo",
    "wof:placetype":"locality"
},
  "geometry": {"coordinates":[1.24861,6.475],"type":"Point"}
}