{
  "type": "Feature",
  "properties": {
    "gn:admin1_code":"0.0",
    "gn:asciiname":"Adossa",
    "gn:country_code":"TG",
    "gn:dem":569,
    "gn:feature_class":"P",
    "gn:feature_code":"PPL",
    "gn:name":"Adossa",
    "gn:population":0,
    "gn:timezone":"Africa/Lome",
    "iso:country":"TG",
    "wof:name":"Adossa",
    "wof:placetype":"locality"
},
  "geometry": {"coordinates":[0.68333,7.56667],"type":"Point"}
}