{
  "type": "Feature",
  "properties": {
    "gn:admin1_code":"23.0",
    "gn:asciiname":"Boufale",
    "gn:country_code":"TG",
    "gn:dem":429,
    "gn:feature_class":"P",
    "gn:feature_code":"PPL",
    "gn:name":"Boufal\u00e9",
    "gn:population":0,
    "gn:timezone":"Africa/Lome",
    "iso:country":"TG",
    "name:und_x_variant":[
        "Boufal\u00e9"
    ],
    "wof:name":"Boufale",
    "wof:placetype":"locality"
},
  "geometry": {"coordinates":[1.33167,9.86361],"type":"Point"}
}