{
  "type": "Feature",
  "properties": {
    "gn:admin1_code":"24.0",
    "gn:asciiname":"Aboni Kope",
    "gn:country_code":"TG",
    "gn:dem":29,
    "gn:feature_class":"P",
    "gn:feature_code":"PPL",
    "gn:name":"Aboni Kop\u00e9",
    "gn:population":0,
    "gn:timezone":"Africa/Lome",
    "iso:country":"TG",
    "wof:name":"Aboni Kope",
    "wof:placetype":"locality"
},
  "geometry": {"coordinates":[1.19194,6.17583],"type":"Point"}
}