{
  "type": "Feature",
  "properties": {
    "gn:admin1_code":"0.0",
    "gn:asciiname":"Afidegnigban",
    "gn:cc2":"TG",
    "gn:country_code":"TG",
    "gn:dem":138,
    "gn:feature_class":"P",
    "gn:feature_code":"PPL",
    "gn:name":"Afid\u00e9gnigban",
    "gn:population":0,
    "gn:timezone":"Africa/Lome",
    "iso:country":"TG",
    "name:und_x_variant":[
        "Afid\u00e9gnigba",
        "Afid\u00e9gnigban"
    ],
    "wof:name":"Afidegnigban",
    "wof:placetype":"locality"
},
  "geometry": {"coordinates":[1.28333,7.38333],"type":"Point"}
}