{
  "type": "Feature",
  "properties": {
    "gn:admin1_code":"0.0",
    "gn:asciiname":"Konkoa",
    "gn:country_code":"TG",
    "gn:dem":653,
    "gn:feature_class":"P",
    "gn:feature_code":"PPL",
    "gn:name":"Konkoa",
    "gn:population":0,
    "gn:timezone":"Africa/Lome",
    "iso:country":"TG",
    "wof:name":"Konkoa",
    "wof:placetype":"locality"
},
  "geometry": {"coordinates":[0.68333,8.18333],"type":"Point"}
}