{
  "type": "Feature",
  "properties": {
    "gn:admin1_code":"0.0",
    "gn:asciiname":"Kassori",
    "gn:country_code":"TG",
    "gn:dem":113,
    "gn:feature_class":"P",
    "gn:feature_code":"PPL",
    "gn:name":"Kassori",
    "gn:population":0,
    "gn:timezone":"Africa/Lome",
    "iso:country":"TG",
    "wof:name":"Kassori",
    "wof:placetype":"locality"
},
  "geometry": {"coordinates":[0.41667,10.06667],"type":"Point"}
}