{
  "type": "Feature",
  "properties": {
    "iso:country":"TG",
    "name:deu_x_preferred":[
        "Kant\u00e9"
    ],
    "name:fra_x_preferred":[
        "Kant\u00e9"
    ],
    "qs:gn_pop":0,
    "qs:name":"Kant\u00e9",
    "qs:name_adm0":"Togo",
    "qs:name_adm1":"Kara",
    "qs:photos":13,
    "qs:photos_1k":3,
    "qs:photos_9k":1,
    "qs:photos_9r":1,
    "qs:photos_all":13,
    "qs:photos_sr":1,
    "qs:placetype":"Town",
    "qs:pop_sr":"0",
    "qs:woe_adm0":23424965,
    "wd:wordcount":73,
    "wof:name":"Kant\u00e9",
    "wof:placetype":"locality"
},
  "geometry": {"coordinates":[1.052627,9.959382],"type":"Point"}
}