{
  "type": "Feature",
  "properties": {
    "gn:admin1_code":"0.0",
    "gn:asciiname":"Atinndou",
    "gn:cc2":"TG",
    "gn:country_code":"TG",
    "gn:dem":112,
    "gn:feature_class":"P",
    "gn:feature_code":"PPL",
    "gn:name":"Atinndou",
    "gn:population":0,
    "gn:timezone":"Africa/Lome",
    "iso:country":"TG",
    "name:und_x_variant":[
        "Atindou",
        "Atinndou"
    ],
    "wof:name":"Atinndou",
    "wof:placetype":"locality"
},
  "geometry": {"coordinates":[1.15,6.51667],"type":"Point"}
}