{
  "type": "Feature",
  "properties": {
    "gn:admin1_code":"0.0",
    "gn:asciiname":"Tambatodeni",
    "gn:country_code":"TG",
    "gn:dem":206,
    "gn:feature_class":"P",
    "gn:feature_code":"PPL",
    "gn:name":"Tambatod\u00e9ni",
    "gn:population":0,
    "gn:timezone":"Africa/Lome",
    "iso:country":"TG",
    "name:und_x_variant":[
        "Tambatod\u00e9ni",
        "Tanbatod\u00e9ni",
        "Koundjouar\u00e9",
        "Koundjoar\u00e9"
    ],
    "wof:name":"Tambatodeni",
    "wof:placetype":"locality"
},
  "geometry": {"coordinates":[0.6438,10.94346],"type":"Point"}
}