{
  "type": "Feature",
  "properties": {
    "gn:admin1_code":"0.0",
    "gn:asciiname":"Doeve",
    "gn:cc2":"TG",
    "gn:country_code":"TG",
    "gn:dem":115,
    "gn:feature_class":"P",
    "gn:feature_code":"PPL",
    "gn:name":"Do\u00e9v\u00e9",
    "gn:population":0,
    "gn:timezone":"Africa/Lome",
    "iso:country":"TG",
    "name:und_x_variant":[
        "D\u00e9ve",
        "Do\u00e9v\u00e9"
    ],
    "wof:name":"Doeve",
    "wof:placetype":"locality"
},
  "geometry": {"coordinates":[1.06667,6.61667],"type":"Point"}
}