{
  "type": "Feature",
  "properties": {
    "gn:admin1_code":"0.0",
    "gn:asciiname":"Matekouo",
    "gn:country_code":"TG",
    "gn:dem":166,
    "gn:feature_class":"P",
    "gn:feature_code":"PPL",
    "gn:name":"Mat\u00e9kouo",
    "gn:population":0,
    "gn:timezone":"Africa/Lome",
    "iso:country":"TG",
    "wof:name":"Matekouo",
    "wof:placetype":"locality"
},
  "geometry": {"coordinates":[1.23333,7.56667],"type":"Point"}
}