{
  "type": "Feature",
  "properties": {
    "gn:admin1_code":"24.0",
    "gn:asciiname":"Yovo Kope",
    "gn:country_code":"TG",
    "gn:dem":11,
    "gn:feature_class":"P",
    "gn:feature_code":"PPL",
    "gn:name":"Yovo Kop\u00e9",
    "gn:population":0,
    "gn:timezone":"Africa/Lome",
    "iso:country":"TG",
    "wof:name":"Yovo Kope",
    "wof:placetype":"locality"
},
  "geometry": {"coordinates":[1.37667,6.18222],"type":"Point"}
}