{
  "type": "Feature",
  "properties": {
    "gn:admin1_code":"24.0",
    "gn:asciiname":"Kouasi Agbavi",
    "gn:country_code":"TG",
    "gn:dem":67,
    "gn:feature_class":"P",
    "gn:feature_code":"PPL",
    "gn:name":"Kouasi Agbavi",
    "gn:population":0,
    "gn:timezone":"Africa/Lome",
    "iso:country":"TG",
    "wof:name":"Kouasi Agbavi",
    "wof:placetype":"locality"
},
  "geometry": {"coordinates":[1.39833,6.17833],"type":"Point"}
}