{
  "type": "Feature",
  "properties": {
    "gn:admin1_code":"0.0",
    "gn:asciiname":"Vedekou",
    "gn:country_code":"TG",
    "gn:dem":63,
    "gn:feature_class":"P",
    "gn:feature_code":"PPL",
    "gn:name":"V\u00e9d\u00e9kou",
    "gn:population":0,
    "gn:timezone":"Africa/Lome",
    "iso:country":"TG",
    "wof:name":"Vedekou",
    "wof:placetype":"locality"
},
  "geometry": {"coordinates":[1.28333,6.43333],"type":"Point"}
}