{
  "type": "Feature",
  "properties": {
    "gn:admin1_code":"0.0",
    "gn:asciiname":"Garbade",
    "gn:cc2":"TG",
    "gn:country_code":"TG",
    "gn:dem":245,
    "gn:feature_class":"P",
    "gn:feature_code":"PPL",
    "gn:name":"Garbad\u00e9",
    "gn:population":0,
    "gn:timezone":"Africa/Lome",
    "iso:country":"TG",
    "name:deu_x_preferred":[
        "Garbade"
    ],
    "name:spa_x_preferred":[
        "Garbade"
    ],
    "name:und_x_variant":[
        "Guarbad\u00e9",
        "Garbad\u00e9"
    ],
    "wof:name":"Garbade",
    "wof:placetype":"locality"
},
  "geometry": {"coordinates":[0.98333,7.96667],"type":"Point"}
}