{
  "type": "Feature",
  "properties": {
    "gn:admin1_code":"0.0",
    "gn:asciiname":"Sessikouravi",
    "gn:country_code":"TG",
    "gn:dem":227,
    "gn:feature_class":"P",
    "gn:feature_code":"PPL",
    "gn:name":"S\u00e9ssikouravi",
    "gn:population":0,
    "gn:timezone":"Africa/Lome",
    "iso:country":"TG",
    "wof:name":"Sessikouravi",
    "wof:placetype":"locality"
},
  "geometry": {"coordinates":[1.03333,8.01667],"type":"Point"}
}