{
  "type": "Feature",
  "properties": {
    "iso:country":"TG",
    "name:und_x_variant":[
        "Anfoi"
    ],
    "qs:gn_country":"TG",
    "qs:gn_fcode":"PPL",
    "qs:gn_pop":0,
    "qs:name":"Anfoin",
    "qs:name_adm0":"Togo",
    "qs:name_adm1":"Maritime",
    "qs:photos":53,
    "qs:photos_1k":11,
    "qs:photos_9k":1,
    "qs:photos_9r":2,
    "qs:photos_all":53,
    "qs:photos_sr":2,
    "qs:placetype":"Town",
    "qs:pop_sr":"0",
    "qs:woe_adm0":23424965,
    "wof:name":"Anfoin",
    "wof:placetype":"locality"
},
  "geometry": {"coordinates":[1.61667,6.31667],"type":"Point"}
}