{
  "type": "Feature",
  "properties": {
    "gn:admin1_code":"24.0",
    "gn:asciiname":"Sidomi",
    "gn:country_code":"TG",
    "gn:dem":3,
    "gn:feature_class":"P",
    "gn:feature_code":"PPL",
    "gn:name":"Sidomi",
    "gn:population":0,
    "gn:timezone":"Africa/Lome",
    "iso:country":"TG",
    "wof:name":"Sidomi",
    "wof:placetype":"locality"
},
  "geometry": {"coordinates":[1.33583,6.2225],"type":"Point"}
}