{
  "type": "Feature",
  "properties": {
    "gn:admin1_code":"0.0",
    "gn:asciiname":"Wadande",
    "gn:country_code":"TG",
    "gn:dem":300,
    "gn:feature_class":"P",
    "gn:feature_code":"PPL",
    "gn:name":"Wadand\u00e9",
    "gn:population":0,
    "gn:timezone":"Africa/Lome",
    "iso:country":"TG",
    "wof:name":"Wadande",
    "wof:placetype":"locality"
},
  "geometry": {"coordinates":[0.76667,9.26667],"type":"Point"}
}