{
  "type": "Feature",
  "properties": {
    "gn:admin1_code":"0.0",
    "gn:asciiname":"Dafolenyame",
    "gn:cc2":"TG",
    "gn:country_code":"TG",
    "gn:dem":67,
    "gn:feature_class":"P",
    "gn:feature_code":"PPL",
    "gn:name":"Dafol\u00e9nyam\u00e9",
    "gn:population":0,
    "gn:timezone":"Africa/Lome",
    "iso:country":"TG",
    "name:und_x_variant":[
        "Dafol\u00e9am\u00e9",
        "Dafol\u00e9nyam\u00e9"
    ],
    "wof:name":"Dafolenyame",
    "wof:placetype":"locality"
},
  "geometry": {"coordinates":[1.05,6.51667],"type":"Point"}
}