{
  "type": "Feature",
  "properties": {
    "gn:admin1_code":"0.0",
    "gn:asciiname":"Amavi Kope",
    "gn:country_code":"TG",
    "gn:dem":49,
    "gn:feature_class":"P",
    "gn:feature_code":"PPL",
    "gn:name":"Amavi Kop\u00e9",
    "gn:population":0,
    "gn:timezone":"Africa/Lome",
    "iso:country":"TG",
    "wof:name":"Amavi Kope",
    "wof:placetype":"locality"
},
  "geometry": {"coordinates":[1.55,6.48333],"type":"Point"}
}