{
  "type": "Feature",
  "properties": {
    "gn:admin1_code":"24.0",
    "gn:asciiname":"Aisou",
    "gn:country_code":"TG",
    "gn:dem":21,
    "gn:feature_class":"P",
    "gn:feature_code":"PPL",
    "gn:name":"Aisou",
    "gn:population":0,
    "gn:timezone":"Africa/Lome",
    "iso:country":"TG",
    "wof:name":"Aisou",
    "wof:placetype":"locality"
},
  "geometry": {"coordinates":[1.49278,6.24361],"type":"Point"}
}