{
  "type": "Feature",
  "properties": {
    "gn:admin1_code":"0.0",
    "gn:asciiname":"Okeloukoutou",
    "gn:country_code":"TG",
    "gn:dem":234,
    "gn:feature_class":"P",
    "gn:feature_code":"PPL",
    "gn:name":"Ok\u00e9loukoutou",
    "gn:population":0,
    "gn:timezone":"Africa/Lome",
    "iso:country":"TG",
    "wof:name":"Okeloukoutou",
    "wof:placetype":"locality"
},
  "geometry": {"coordinates":[1.43333,7.73333],"type":"Point"}
}