{
  "type": "Feature",
  "properties": {
    "gn:admin1_code":"0.0",
    "gn:asciiname":"Amake",
    "gn:country_code":"TG",
    "gn:dem":78,
    "gn:feature_class":"P",
    "gn:feature_code":"PPL",
    "gn:name":"Amak\u00e9",
    "gn:population":0,
    "gn:timezone":"Africa/Lome",
    "iso:country":"TG",
    "wof:name":"Amake",
    "wof:placetype":"locality"
},
  "geometry": {"coordinates":[0.95,6.41667],"type":"Point"}
}