{
  "type": "Feature",
  "properties": {
    "gn:admin1_code":"24.0",
    "gn:asciiname":"Diassekope",
    "gn:country_code":"TG",
    "gn:dem":71,
    "gn:feature_class":"P",
    "gn:feature_code":"PPL",
    "gn:name":"Diass\u00e9kop\u00e9",
    "gn:population":0,
    "gn:timezone":"Africa/Lome",
    "iso:country":"TG",
    "name:und_x_variant":[
        "Dios\u00e9 Kop\u00e9",
        "Diass\u00e9kop\u00e9"
    ],
    "wof:name":"Diassekope",
    "wof:placetype":"locality"
},
  "geometry": {"coordinates":[1.10278,6.30111],"type":"Point"}
}