{
  "type": "Feature",
  "properties": {
    "gn:admin1_code":"0.0",
    "gn:asciiname":"Dassikope",
    "gn:cc2":"TG",
    "gn:country_code":"TG",
    "gn:dem":87,
    "gn:feature_class":"P",
    "gn:feature_code":"PPL",
    "gn:name":"Dassikop\u00e9",
    "gn:population":0,
    "gn:timezone":"Africa/Lome",
    "iso:country":"TG",
    "name:und_x_variant":[
        "Avogo",
        "Dasi Kop\u00e9",
        "Dassikop\u00e9"
    ],
    "wof:name":"Dassikope",
    "wof:placetype":"locality"
},
  "geometry": {"coordinates":[0.91667,6.58333],"type":"Point"}
}