{
  "type": "Feature",
  "properties": {
    "gn:admin1_code":"0.0",
    "gn:asciiname":"Danhadanha",
    "gn:country_code":"TG",
    "gn:dem":328,
    "gn:feature_class":"P",
    "gn:feature_code":"PPL",
    "gn:name":"Danhadanha",
    "gn:population":0,
    "gn:timezone":"Africa/Lome",
    "iso:country":"TG",
    "wof:name":"Danhadanha",
    "wof:placetype":"locality"
},
  "geometry": {"coordinates":[1.36667,8.75],"type":"Point"}
}