{
  "type": "Feature",
  "properties": {
    "gn:admin1_code":"0.0",
    "gn:asciiname":"Wouley",
    "gn:country_code":"TG",
    "gn:dem":146,
    "gn:feature_class":"P",
    "gn:feature_code":"PPL",
    "gn:name":"Wouley",
    "gn:population":0,
    "gn:timezone":"Africa/Lome",
    "iso:country":"TG",
    "wof:name":"Wouley",
    "wof:placetype":"locality"
},
  "geometry": {"coordinates":[1.08333,6.91667],"type":"Point"}
}