{
  "type": "Feature",
  "properties": {
    "gn:admin1_code":"0.0",
    "gn:asciiname":"Nyigbe",
    "gn:cc2":"TG",
    "gn:country_code":"TG",
    "gn:dem":123,
    "gn:feature_class":"P",
    "gn:feature_code":"PPL",
    "gn:name":"Nyigb\u00e9",
    "gn:population":0,
    "gn:timezone":"Africa/Lome",
    "iso:country":"TG",
    "name:und_x_variant":[
        "Nyibo",
        "Nyigb\u00e9"
    ],
    "wof:name":"Nyigbe",
    "wof:placetype":"locality"
},
  "geometry": {"coordinates":[1.13333,6.68333],"type":"Point"}
}