{
  "type": "Feature",
  "properties": {
    "gn:admin1_code":"0.0",
    "gn:asciiname":"Avoukouekope",
    "gn:country_code":"TG",
    "gn:dem":190,
    "gn:feature_class":"P",
    "gn:feature_code":"PPL",
    "gn:name":"Avoukou\u00e9kop\u00e9",
    "gn:population":0,
    "gn:timezone":"Africa/Lome",
    "iso:country":"TG",
    "wof:name":"Avoukouekope",
    "wof:placetype":"locality"
},
  "geometry": {"coordinates":[1.01667,7.18333],"type":"Point"}
}