{
  "type": "Feature",
  "properties": {
    "gn:admin1_code":"0.0",
    "gn:asciiname":"Amenoukpe",
    "gn:cc2":"TG",
    "gn:country_code":"TG",
    "gn:dem":109,
    "gn:feature_class":"P",
    "gn:feature_code":"PPL",
    "gn:name":"Am\u00e9noukp\u00e9",
    "gn:population":0,
    "gn:timezone":"Africa/Lome",
    "iso:country":"TG",
    "name:und_x_variant":[
        "Menoukpo\u00e9",
        "Am\u00e9noukp\u00e9"
    ],
    "wof:name":"Amenoukpe",
    "wof:placetype":"locality"
},
  "geometry": {"coordinates":[0.93333,6.48333],"type":"Point"}
}