{
  "type": "Feature",
  "properties": {
    "gn:admin1_code":"0.0",
    "gn:asciiname":"Kankangbe",
    "gn:country_code":"TG",
    "gn:dem":127,
    "gn:feature_class":"P",
    "gn:feature_code":"PPL",
    "gn:name":"Kankangb\u00e9",
    "gn:population":0,
    "gn:timezone":"Africa/Lome",
    "iso:country":"TG",
    "wof:name":"Kankangbe",
    "wof:placetype":"locality"
},
  "geometry": {"coordinates":[0.61667,10.16667],"type":"Point"}
}