{
  "type": "Feature",
  "properties": {
    "gn:admin1_code":"0.0",
    "gn:asciiname":"Badji",
    "gn:country_code":"TG",
    "gn:dem":169,
    "gn:feature_class":"P",
    "gn:feature_code":"PPL",
    "gn:name":"Badji",
    "gn:population":0,
    "gn:timezone":"Africa/Lome",
    "iso:country":"TG",
    "wof:name":"Badji",
    "wof:placetype":"locality"
},
  "geometry": {"coordinates":[1.35,7.38333],"type":"Point"}
}