{
  "type": "Feature",
  "properties": {
    "gn:admin1_code":"24.0",
    "gn:asciiname":"Kpogan",
    "gn:country_code":"TG",
    "gn:dem":67,
    "gn:feature_class":"P",
    "gn:feature_code":"PPL",
    "gn:name":"Kpogan",
    "gn:population":0,
    "gn:timezone":"Africa/Lome",
    "iso:country":"TG",
    "name:und_x_variant":[
        "Pogan",
        "Kpogan"
    ],
    "wof:name":"Kpogan",
    "wof:placetype":"locality"
},
  "geometry": {"coordinates":[1.3825,6.17278],"type":"Point"}
}