{
  "type": "Feature",
  "properties": {
    "gn:admin1_code":"23.0",
    "gn:asciiname":"Pya",
    "gn:country_code":"TG",
    "gn:dem":386,
    "gn:feature_class":"P",
    "gn:feature_code":"PPL",
    "gn:name":"Pya",
    "gn:population":0,
    "gn:timezone":"Africa/Lome",
    "iso:country":"TG",
    "name:und_x_variant":[
        "Piya",
        "Pya"
    ],
    "wof:name":"Pya",
    "wof:placetype":"locality"
},
  "geometry": {"coordinates":[1.15,9.66667],"type":"Point"}
}