{
  "type": "Feature",
  "properties": {
    "gn:admin1_code":"24.0",
    "gn:asciiname":"Amou",
    "gn:country_code":"TG",
    "gn:dem":38,
    "gn:feature_class":"P",
    "gn:feature_code":"PPL",
    "gn:name":"Amou",
    "gn:population":0,
    "gn:timezone":"Africa/Lome",
    "iso:country":"TG",
    "wof:name":"Amou",
    "wof:placetype":"locality"
},
  "geometry": {"coordinates":[1.20333,6.215],"type":"Point"}
}