{
  "type": "Feature",
  "properties": {
    "gn:admin1_code":"24.0",
    "gn:asciiname":"Amou",
    "gn:country_code":"TG",
    "gn:dem":38,
    "gn:feature_class":"P",
    "gn:feature_code":"PPL",
    "gn:name":"Amou",
    "gn:population":0,
    "gn:timezone":"Africa/Lome",
    "iso:country":"TG",
    "name:ceb_x_preferred":[
        "Amou"
    ],
    "name:fra_x_preferred":[
        "Amou"
    ],
    "name:ita_x_preferred":[
        "Amou"
    ],
    "name:nld_x_preferred":[
        "Amou"
    ],
    "name:slk_x_preferred":[
        "Amou"
    ],
    "name:swe_x_preferred":[
        "Amou"
    ],
    "wof:name":"Amou",
    "wof:placetype":"locality"
},
  "geometry": {"coordinates":[1.20333,6.215],"type":"Point"}
}