{
  "type": "Feature",
  "properties": {
    "gn:admin1_code":"0.0",
    "gn:asciiname":"Basse Gnamassi",
    "gn:country_code":"TG",
    "gn:dem":210,
    "gn:feature_class":"P",
    "gn:feature_code":"PPL",
    "gn:name":"Bass\u00e9 Gnamassi",
    "gn:population":0,
    "gn:timezone":"Africa/Lome",
    "iso:country":"TG",
    "wof:name":"Basse Gnamassi",
    "wof:placetype":"locality"
},
  "geometry": {"coordinates":[1.06667,7.35],"type":"Point"}
}