{
  "type": "Feature",
  "properties": {
    "gn:admin1_code":"24.0",
    "gn:asciiname":"Koumako",
    "gn:country_code":"TG",
    "gn:dem":0,
    "gn:feature_class":"P",
    "gn:feature_code":"PPL",
    "gn:name":"Koumako",
    "gn:population":0,
    "gn:timezone":"Africa/Lome",
    "iso:country":"TG",
    "wof:name":"Koumako",
    "wof:placetype":"locality"
},
  "geometry": {"coordinates":[1.4975,6.23167],"type":"Point"}
}