{
  "type": "Feature",
  "properties": {
    "gn:admin1_code":"0.0",
    "gn:asciiname":"Sabarangade",
    "gn:country_code":"TG",
    "gn:dem":344,
    "gn:feature_class":"P",
    "gn:feature_code":"PPL",
    "gn:name":"Sabarangad\u00e9",
    "gn:population":0,
    "gn:timezone":"Africa/Lome",
    "iso:country":"TG",
    "wof:name":"Sabarangade",
    "wof:placetype":"locality"
},
  "geometry": {"coordinates":[1.33333,8.98333],"type":"Point"}
}