{
  "type": "Feature",
  "properties": {
    "gn:admin1_code":"0.0",
    "gn:asciiname":"Boulohou",
    "gn:country_code":"TG",
    "gn:dem":307,
    "gn:feature_class":"P",
    "gn:feature_code":"PPL",
    "gn:name":"Boulohou",
    "gn:population":0,
    "gn:timezone":"Africa/Lome",
    "iso:country":"TG",
    "name:und_x_variant":[
        "Gboloho",
        "Boulo",
        "Boulohou"
    ],
    "wof:name":"Boulohou",
    "wof:placetype":"locality"
},
  "geometry": {"coordinates":[0.67232,8.76648],"type":"Point"}
}