{
  "type": "Feature",
  "properties": {
    "gn:admin1_code":"0.0",
    "gn:asciiname":"Adiakiti",
    "gn:country_code":"TG",
    "gn:dem":261,
    "gn:feature_class":"P",
    "gn:feature_code":"PPL",
    "gn:name":"Adiakiti",
    "gn:population":0,
    "gn:timezone":"Africa/Lome",
    "iso:country":"TG",
    "wof:name":"Adiakiti",
    "wof:placetype":"locality"
},
  "geometry": {"coordinates":[1.56667,8.05],"type":"Point"}
}