{
  "type": "Feature",
  "properties": {
    "gn:admin1_code":"0.0",
    "gn:asciiname":"Agadjakpe",
    "gn:country_code":"TG",
    "gn:dem":86,
    "gn:feature_class":"P",
    "gn:feature_code":"PPL",
    "gn:name":"Agadjakp\u00e9",
    "gn:population":0,
    "gn:timezone":"Africa/Lome",
    "iso:country":"TG",
    "wof:name":"Agadjakpe",
    "wof:placetype":"locality"
},
  "geometry": {"coordinates":[1.06667,6.55],"type":"Point"}
}