{
  "type": "Feature",
  "properties": {
    "gn:admin1_code":"24.0",
    "gn:asciiname":"Avegwime",
    "gn:country_code":"TG",
    "gn:dem":41,
    "gn:feature_class":"P",
    "gn:feature_code":"PPL",
    "gn:name":"Av\u00e9gwim\u00e9",
    "gn:population":0,
    "gn:timezone":"Africa/Lome",
    "iso:country":"TG",
    "wof:name":"Avegwime",
    "wof:placetype":"locality"
},
  "geometry": {"coordinates":[1.09722,6.20694],"type":"Point"}
}