{
  "type": "Feature",
  "properties": {
    "gn:admin1_code":"0.0",
    "gn:asciiname":"Agbodjekpo",
    "gn:country_code":"TG",
    "gn:dem":150,
    "gn:feature_class":"P",
    "gn:feature_code":"PPL",
    "gn:name":"Agbodjekpo",
    "gn:population":0,
    "gn:timezone":"Africa/Lome",
    "iso:country":"TG",
    "wof:name":"Agbodjekpo",
    "wof:placetype":"locality"
},
  "geometry": {"coordinates":[1.01667,6.83333],"type":"Point"}
}