{
  "type": "Feature",
  "properties": {
    "gn:admin1_code":"0.0",
    "gn:asciiname":"Togarhaouide",
    "gn:country_code":"TG",
    "gn:dem":381,
    "gn:feature_class":"P",
    "gn:feature_code":"PPL",
    "gn:name":"Togarhaouid\u00e9",
    "gn:population":0,
    "gn:timezone":"Africa/Lome",
    "iso:country":"TG",
    "name:und_x_variant":[
        "Togarhaouid\u00e9"
    ],
    "wof:name":"Togarhaouide",
    "wof:placetype":"locality"
},
  "geometry": {"coordinates":[1.21667,9.96667],"type":"Point"}
}