{
  "type": "Feature",
  "properties": {
    "gn:admin1_code":"0.0",
    "gn:asciiname":"Amoussa",
    "gn:country_code":"TG",
    "gn:dem":603,
    "gn:feature_class":"P",
    "gn:feature_code":"PPL",
    "gn:name":"Amoussa",
    "gn:population":0,
    "gn:timezone":"Africa/Lome",
    "iso:country":"TG",
    "wof:name":"Amoussa",
    "wof:placetype":"locality"
},
  "geometry": {"coordinates":[0.98333,7.58333],"type":"Point"}
}