{
  "type": "Feature",
  "properties": {
    "gn:admin1_code":"0.0",
    "gn:asciiname":"Pesside Koundoum",
    "gn:country_code":"TG",
    "gn:dem":262,
    "gn:feature_class":"P",
    "gn:feature_code":"PPL",
    "gn:name":"Pessid\u00e9 Koundoum",
    "gn:population":0,
    "gn:timezone":"Africa/Lome",
    "iso:country":"TG",
    "name:fra_x_preferred":[
        "Pesside Koundoum"
    ],
    "name:und_x_variant":[
        "Pessid\u00e9 Koundoum"
    ],
    "wof:name":"Pesside Koundoum",
    "wof:placetype":"locality"
},
  "geometry": {"coordinates":[0.88333,9.55],"type":"Point"}
}