{
  "type": "Feature",
  "properties": {
    "gn:admin1_code":"0.0",
    "gn:asciiname":"Nabangou",
    "gn:country_code":"TG",
    "gn:dem":335,
    "gn:feature_class":"P",
    "gn:feature_code":"PPL",
    "gn:name":"Nabangou",
    "gn:population":0,
    "gn:timezone":"Africa/Lome",
    "iso:country":"TG",
    "wof:name":"Nabangou",
    "wof:placetype":"locality"
},
  "geometry": {"coordinates":[0.35,10.76667],"type":"Point"}
}