{
  "type": "Feature",
  "properties": {
    "gn:admin1_code":"0.0",
    "gn:asciiname":"Kotateou",
    "gn:country_code":"TG",
    "gn:dem":117,
    "gn:feature_class":"P",
    "gn:feature_code":"PPL",
    "gn:name":"Kotat\u00e9ou",
    "gn:population":0,
    "gn:timezone":"Africa/Lome",
    "iso:country":"TG",
    "name:und_x_variant":[
        "Kotat\u00e9ou"
    ],
    "wof:name":"Kotateou",
    "wof:placetype":"locality"
},
  "geometry": {"coordinates":[0.41667,9.68333],"type":"Point"}
}