{
  "type": "Feature",
  "properties": {
    "gn:admin1_code":"0.0",
    "gn:asciiname":"Diadiaba",
    "gn:country_code":"TG",
    "gn:dem":112,
    "gn:feature_class":"P",
    "gn:feature_code":"PPL",
    "gn:name":"Diadiaba",
    "gn:population":0,
    "gn:timezone":"Africa/Lome",
    "iso:country":"TG",
    "wof:name":"Diadiaba",
    "wof:placetype":"locality"
},
  "geometry": {"coordinates":[0.36667,9.85],"type":"Point"}
}