{
  "type": "Feature",
  "properties": {
    "gn:admin1_code":"24.0",
    "gn:asciiname":"Vo Asso",
    "gn:country_code":"TG",
    "gn:dem":86,
    "gn:feature_class":"P",
    "gn:feature_code":"PPL",
    "gn:name":"Vo Asso",
    "gn:population":0,
    "gn:timezone":"Africa/Lome",
    "iso:country":"TG",
    "name:und_x_variant":[
        "Aso",
        "Vo-Aso",
        "Woaso",
        "Vo Asso"
    ],
    "wof:name":"Vo Asso",
    "wof:placetype":"locality"
},
  "geometry": {"coordinates":[1.47417,6.48917],"type":"Point"}
}