{
  "type": "Feature",
  "properties": {
    "gn:admin1_code":"0.0",
    "gn:asciiname":"Esse Zogbedji",
    "gn:cc2":"TG",
    "gn:country_code":"TG",
    "gn:dem":59,
    "gn:feature_class":"P",
    "gn:feature_code":"PPL",
    "gn:name":"Ess\u00e9 Zogbedji",
    "gn:population":0,
    "gn:timezone":"Africa/Lome",
    "iso:country":"TG",
    "name:und_x_variant":[
        "Sogh\u00e9dji",
        "Es\u00e9 Zogbedji",
        "Sogb\u00e9dji",
        "Ess\u00e9 Zogbedji"
    ],
    "wof:name":"Esse Zogbedji",
    "wof:placetype":"locality"
},
  "geometry": {"coordinates":[1.33333,6.58333],"type":"Point"}
}