{
  "type": "Feature",
  "properties": {
    "gn:admin1_code":"0.0",
    "gn:asciiname":"Djodje",
    "gn:country_code":"TG",
    "gn:dem":71,
    "gn:feature_class":"P",
    "gn:feature_code":"PPL",
    "gn:name":"Djodj\u00e9",
    "gn:population":0,
    "gn:timezone":"Africa/Lome",
    "iso:country":"TG",
    "wof:name":"Djodje",
    "wof:placetype":"locality"
},
  "geometry": {"coordinates":[1.03333,6.26667],"type":"Point"}
}