{
  "type": "Feature",
  "properties": {
    "gn:admin1_code":"0.0",
    "gn:asciiname":"Atchassi",
    "gn:cc2":"TG",
    "gn:country_code":"TG",
    "gn:dem":69,
    "gn:feature_class":"P",
    "gn:feature_code":"PPL",
    "gn:name":"Atchassi",
    "gn:population":0,
    "gn:timezone":"Africa/Lome",
    "iso:country":"TG",
    "name:und_x_variant":[
        "Atchasi",
        "Atchassi"
    ],
    "wof:name":"Atchassi",
    "wof:placetype":"locality"
},
  "geometry": {"coordinates":[1.55,6.45],"type":"Point"}
}