{
  "type": "Feature",
  "properties": {
    "gn:admin1_code":"0.0",
    "gn:asciiname":"Taman",
    "gn:country_code":"TG",
    "gn:dem":110,
    "gn:feature_class":"P",
    "gn:feature_code":"PPL",
    "gn:name":"Taman",
    "gn:population":0,
    "gn:timezone":"Africa/Lome",
    "iso:country":"TG",
    "name:ceb_x_preferred":[
        "Taman"
    ],
    "name:deu_x_preferred":[
        "Taman"
    ],
    "name:fra_x_preferred":[
        "Taman"
    ],
    "name:heb_x_preferred":[
        "\u05d8\u05d0\u05de\u05d0\u05df"
    ],
    "name:jpn_x_preferred":[
        "\u30bf\u30de\u30f3"
    ],
    "name:nld_x_preferred":[
        "Taman"
    ],
    "name:nor_x_preferred":[
        "Taman"
    ],
    "name:por_x_preferred":[
        "Taman"
    ],
    "name:swe_x_preferred":[
        "Taman"
    ],
    "name:zho_x_preferred":[
        "Taman"
    ],
    "wof:name":"Taman",
    "wof:placetype":"locality"
},
  "geometry": {"coordinates":[0.25,9.46667],"type":"Point"}
}