{
  "type": "Feature",
  "properties": {
    "gn:admin1_code":"0.0",
    "gn:asciiname":"Kabrekope",
    "gn:country_code":"TG",
    "gn:dem":157,
    "gn:feature_class":"P",
    "gn:feature_code":"PPL",
    "gn:name":"Kabr\u00e9kop\u00e9",
    "gn:population":0,
    "gn:timezone":"Africa/Lome",
    "iso:country":"TG",
    "wof:name":"Kabrekope",
    "wof:placetype":"locality"
},
  "geometry": {"coordinates":[1.11667,7.03333],"type":"Point"}
}