{
  "type": "Feature",
  "properties": {
    "gn:admin1_code":"0.0",
    "gn:asciiname":"Aban",
    "gn:country_code":"TG",
    "gn:dem":364,
    "gn:feature_class":"P",
    "gn:feature_code":"PPL",
    "gn:name":"Aban",
    "gn:population":0,
    "gn:timezone":"Africa/Lome",
    "iso:country":"TG",
    "name:fas_x_preferred":[
        "\u0622\u0628\u0627\u0646\u06af\u0627\u0646"
    ],
    "name:jpn_x_preferred":[
        "\u30a2\u30fc\u30d7"
    ],
    "wof:name":"Aban",
    "wof:placetype":"locality"
},
  "geometry": {"coordinates":[1.31667,9.48333],"type":"Point"}
}