{
  "type": "Feature",
  "properties": {
    "gn:admin1_code":"0.0",
    "gn:asciiname":"Koudyopongpong",
    "gn:cc2":"TG",
    "gn:country_code":"TG",
    "gn:dem":200,
    "gn:feature_class":"P",
    "gn:feature_code":"PPL",
    "gn:name":"Koudyopongpong",
    "gn:population":0,
    "gn:timezone":"Africa/Lome",
    "iso:country":"TG",
    "name:und_x_variant":[
        "Koujioponpon",
        "Koudyopongpong"
    ],
    "wof:name":"Koudyopongpong",
    "wof:placetype":"locality"
},
  "geometry": {"coordinates":[0.63333,9.48333],"type":"Point"}
}