{
  "type": "Feature",
  "properties": {
    "gn:admin1_code":"24.0",
    "gn:asciiname":"Agbanati",
    "gn:country_code":"TG",
    "gn:dem":41,
    "gn:feature_class":"P",
    "gn:feature_code":"PPL",
    "gn:name":"Agbanati",
    "gn:population":0,
    "gn:timezone":"Africa/Lome",
    "iso:country":"TG",
    "wof:name":"Agbanati",
    "wof:placetype":"locality"
},
  "geometry": {"coordinates":[1.10222,6.24028],"type":"Point"}
}