{
  "type": "Feature",
  "properties": {
    "gn:admin1_code":"22.0",
    "gn:asciiname":"Blitta",
    "gn:country_code":"TG",
    "gn:dem":307,
    "gn:feature_class":"P",
    "gn:feature_code":"PPL",
    "gn:name":"Blitta",
    "gn:population":0,
    "gn:timezone":"Africa/Lome",
    "iso:country":"TG",
    "name:frr_x_preferred":[
        "Blitta"
    ],
    "name:por_x_preferred":[
        "Blitta"
    ],
    "name:und_x_variant":[
        "Blita",
        "Blibba",
        "Blita-gare",
        "Bliba",
        "Blitta"
    ],
    "name:zho_x_preferred":[
        "\u5e03\u5229\u5854\u7701"
    ],
    "wof:name":"Blitta",
    "wof:placetype":"locality"
},
  "geometry": {"coordinates":[0.98595,8.32335],"type":"Point"}
}