{
  "type": "Feature",
  "properties": {
    "gn:admin1_code":"0.0",
    "gn:asciiname":"Kpeme",
    "gn:country_code":"TG",
    "gn:dem":111,
    "gn:feature_class":"P",
    "gn:feature_code":"PPL",
    "gn:name":"Kp\u00e9m\u00e9",
    "gn:population":0,
    "gn:timezone":"Africa/Lome",
    "iso:country":"TG",
    "wof:name":"Kpeme",
    "wof:placetype":"locality"
},
  "geometry": {"coordinates":[1.18333,6.43333],"type":"Point"}
}