{
  "type": "Feature",
  "properties": {
    "gn:admin1_code":"24.0",
    "gn:asciiname":"Tokpo",
    "gn:country_code":"TG",
    "gn:dem":27,
    "gn:feature_class":"P",
    "gn:feature_code":"PPL",
    "gn:name":"Tokpo",
    "gn:population":0,
    "gn:timezone":"Africa/Lome",
    "iso:country":"TG",
    "wof:name":"Tokpo",
    "wof:placetype":"locality"
},
  "geometry": {"coordinates":[1.2225,6.20667],"type":"Point"}
}