{
  "type": "Feature",
  "properties": {
    "gn:admin1_code":"0.0",
    "gn:asciiname":"Kpeve",
    "gn:country_code":"TG",
    "gn:dem":107,
    "gn:feature_class":"P",
    "gn:feature_code":"PPL",
    "gn:name":"Kp\u00e9v\u00e9",
    "gn:population":0,
    "gn:timezone":"Africa/Lome",
    "iso:country":"TG",
    "name:deu_x_preferred":[
        "Kpeve"
    ],
    "wof:name":"Kpeve",
    "wof:placetype":"locality"
},
  "geometry": {"coordinates":[1.01667,6.61667],"type":"Point"}
}