{
  "type": "Feature",
  "properties": {
    "gn:admin1_code":"0.0",
    "gn:asciiname":"Bouenaou",
    "gn:country_code":"TG",
    "gn:dem":637,
    "gn:feature_class":"P",
    "gn:feature_code":"PPL",
    "gn:name":"Bou\u00e9naou",
    "gn:population":0,
    "gn:timezone":"Africa/Lome",
    "iso:country":"TG",
    "wof:name":"Bouenaou",
    "wof:placetype":"locality"
},
  "geometry": {"coordinates":[1.01667,7.71667],"type":"Point"}
}