{
  "type": "Feature",
  "properties": {
    "iso:country":"TG",
    "name:fra_x_preferred":[
        "F\u00e9lix Couchoro"
    ],
    "name:glg_x_preferred":[
        "F\u00e9lix Couchoro"
    ],
    "name:ron_x_preferred":[
        "F\u00e9lix Couchoro"
    ],
    "name:spa_x_preferred":[
        "F\u00e9lix Couchoro"
    ],
    "qs:gn_pop":0,
    "qs:name":"An\u00e9cho",
    "qs:name_adm0":"Togo",
    "qs:name_adm1":"Maritime",
    "qs:photos":63,
    "qs:photos_1k":13,
    "qs:photos_9k":1,
    "qs:photos_9r":2,
    "qs:photos_all":63,
    "qs:photos_sr":2,
    "qs:placetype":"Town",
    "qs:pop_sr":"0",
    "qs:woe_adm0":23424965,
    "wof:name":"An\u00e9cho",
    "wof:placetype":"locality"
},
  "geometry": {"coordinates":[1.571044,6.234077],"type":"Point"}
}