{
  "type": "Feature",
  "properties": {
    "gn:admin1_code":"0.0",
    "gn:asciiname":"Anha",
    "gn:cc2":"TG",
    "gn:country_code":"TG",
    "gn:dem":100,
    "gn:feature_class":"P",
    "gn:feature_code":"PPL",
    "gn:name":"Anha",
    "gn:population":0,
    "gn:timezone":"Africa/Lome",
    "iso:country":"TG",
    "name:und_x_variant":[
        "Ana",
        "Anha"
    ],
    "wof:name":"Anha",
    "wof:placetype":"locality"
},
  "geometry": {"coordinates":[0.95,6.48333],"type":"Point"}
}