{
  "type": "Feature",
  "properties": {
    "gn:admin1_code":"0.0",
    "gn:asciiname":"Anha",
    "gn:cc2":"TG",
    "gn:country_code":"TG",
    "gn:dem":100,
    "gn:feature_class":"P",
    "gn:feature_code":"PPL",
    "gn:name":"Anha",
    "gn:population":0,
    "gn:timezone":"Africa/Lome",
    "iso:country":"TG",
    "name:ceb_x_preferred":[
        "Anha"
    ],
    "name:kaz_x_preferred":[
        "\u0412\u0438\u043b\u0430-\u041d\u043e\u0432\u0430-\u0434\u0435-\u0410\u043d\u044c\u044f"
    ],
    "name:msa_x_preferred":[
        "Anha"
    ],
    "name:por_x_preferred":[
        "Anha"
    ],
    "name:rus_x_preferred":[
        "\u0412\u0438\u043b\u0430-\u041d\u043e\u0432\u0430-\u0434\u0435-\u0410\u043d\u044c\u044f"
    ],
    "name:spa_x_preferred":[
        "Anha"
    ],
    "name:tur_x_preferred":[
        "Anha"
    ],
    "name:und_x_variant":[
        "Ana",
        "Anha"
    ],
    "wof:name":"Anha",
    "wof:placetype":"locality"
},
  "geometry": {"coordinates":[0.95,6.48333],"type":"Point"}
}