{
  "type": "Feature",
  "properties": {
    "gn:admin1_code":"24.0",
    "gn:asciiname":"Sakpleto",
    "gn:country_code":"TG",
    "gn:dem":48,
    "gn:feature_class":"P",
    "gn:feature_code":"PPL",
    "gn:name":"Sakpl\u00e9to",
    "gn:population":0,
    "gn:timezone":"Africa/Lome",
    "iso:country":"TG",
    "wof:name":"Sakpleto",
    "wof:placetype":"locality"
},
  "geometry": {"coordinates":[1.16028,6.24111],"type":"Point"}
}