{
  "type": "Feature",
  "properties": {
    "gn:admin1_code":"0.0",
    "gn:asciiname":"Dakondji",
    "gn:country_code":"TG",
    "gn:dem":18,
    "gn:feature_class":"P",
    "gn:feature_code":"PPL",
    "gn:name":"Dakondji",
    "gn:population":0,
    "gn:timezone":"Africa/Lome",
    "iso:country":"TG",
    "wof:name":"Dakondji",
    "wof:placetype":"locality"
},
  "geometry": {"coordinates":[1.66667,6.28333],"type":"Point"}
}