{
  "type": "Feature",
  "properties": {
    "gn:admin1_code":"0.0",
    "gn:asciiname":"Anima",
    "gn:cc2":"TG",
    "gn:country_code":"TG",
    "gn:dem":308,
    "gn:feature_class":"P",
    "gn:feature_code":"PPL",
    "gn:name":"Anima",
    "gn:population":0,
    "gn:timezone":"Africa/Lome",
    "iso:country":"TG",
    "name:und_x_variant":[
        "Undemba",
        "Oundemba",
        "Anima"
    ],
    "wof:name":"Anima",
    "wof:placetype":"locality"
},
  "geometry": {"coordinates":[1.01667,9.76667],"type":"Point"}
}