{
  "type": "Feature",
  "properties": {
    "gn:admin1_code":"0.0",
    "gn:asciiname":"Anima",
    "gn:cc2":"TG",
    "gn:country_code":"TG",
    "gn:dem":308,
    "gn:feature_class":"P",
    "gn:feature_code":"PPL",
    "gn:name":"Anima",
    "gn:population":0,
    "gn:timezone":"Africa/Lome",
    "iso:country":"TG",
    "name:dan_x_preferred":[
        "Anima"
    ],
    "name:deu_x_preferred":[
        "Anima"
    ],
    "name:est_x_preferred":[
        "Anima"
    ],
    "name:fra_x_preferred":[
        "Anima"
    ],
    "name:heb_x_preferred":[
        "\u05d0\u05e0\u05d9\u05de\u05d4"
    ],
    "name:ita_x_preferred":[
        "Anima"
    ],
    "name:jpn_x_preferred":[
        "\u30a2\u30cb\u30de"
    ],
    "name:kur_x_preferred":[
        "An\u00eema"
    ],
    "name:nld_x_preferred":[
        "Anima"
    ],
    "name:por_x_preferred":[
        "Anima"
    ],
    "name:slk_x_preferred":[
        "Anima"
    ],
    "name:spa_x_preferred":[
        "\u00c1nima"
    ],
    "name:tgl_x_preferred":[
        "Anima"
    ],
    "name:tur_x_preferred":[
        "Anima"
    ],
    "name:und_x_variant":[
        "Undemba",
        "Oundemba"
    ],
    "wof:name":"Anima",
    "wof:placetype":"locality"
},
  "geometry": {"coordinates":[1.01667,9.76667],"type":"Point"}
}