{
  "type": "Feature",
  "properties": {
    "gn:admin1_code":"24.0",
    "gn:asciiname":"Amokwi",
    "gn:country_code":"TG",
    "gn:dem":48,
    "gn:feature_class":"P",
    "gn:feature_code":"PPL",
    "gn:name":"Amokwi",
    "gn:population":0,
    "gn:timezone":"Africa/Lome",
    "iso:country":"TG",
    "name:und_x_variant":[
        "Amokouy",
        "Amokwi"
    ],
    "wof:name":"Amokwi",
    "wof:placetype":"locality"
},
  "geometry": {"coordinates":[1.1675,6.2425],"type":"Point"}
}