{
  "type": "Feature",
  "properties": {
    "gn:admin1_code":"0.0",
    "gn:asciiname":"Abokoukope",
    "gn:country_code":"TG",
    "gn:dem":214,
    "gn:feature_class":"P",
    "gn:feature_code":"PPL",
    "gn:name":"Abokoukop\u00e9",
    "gn:population":0,
    "gn:timezone":"Africa/Lome",
    "iso:country":"TG",
    "wof:name":"Abokoukope",
    "wof:placetype":"locality"
},
  "geometry": {"coordinates":[1.08333,7.55],"type":"Point"}
}