{
  "type": "Feature",
  "properties": {
    "gn:admin1_code":"24.0",
    "gn:asciiname":"Kpodo",
    "gn:country_code":"TG",
    "gn:dem":44,
    "gn:feature_class":"P",
    "gn:feature_code":"PPL",
    "gn:name":"Kpodo",
    "gn:population":0,
    "gn:timezone":"Africa/Lome",
    "iso:country":"TG",
    "wof:name":"Kpodo",
    "wof:placetype":"locality"
},
  "geometry": {"coordinates":[1.13028,6.23278],"type":"Point"}
}