{
  "type": "Feature",
  "properties": {
    "gn:asciiname":"Keve",
    "gn:country_code":"TG",
    "gn:dem":38,
    "gn:feature_class":"P",
    "gn:feature_code":"PPL",
    "gn:name":"Keve",
    "gn:population":0,
    "gn:timezone":"Africa/Lome",
    "iso:country":"TG",
    "wof:name":"Keve",
    "wof:placetype":"locality"
},
  "geometry": {"coordinates":[1.10095,6.24787],"type":"Point"}
}