{
  "type": "Feature",
  "properties": {
    "gn:admin1_code":"0.0",
    "gn:asciiname":"Naware",
    "gn:country_code":"TG",
    "gn:dem":109,
    "gn:feature_class":"P",
    "gn:feature_code":"PPL",
    "gn:name":"Nawar\u00e9",
    "gn:population":0,
    "gn:timezone":"Africa/Lome",
    "iso:country":"TG",
    "wof:name":"Naware",
    "wof:placetype":"locality"
},
  "geometry": {"coordinates":[0.31667,9.55],"type":"Point"}
}