{
  "type": "Feature",
  "properties": {
    "gn:admin1_code":"0.0",
    "gn:asciiname":"Zowola Kpoguede",
    "gn:cc2":"TG",
    "gn:country_code":"TG",
    "gn:dem":22,
    "gn:feature_class":"P",
    "gn:feature_code":"PPL",
    "gn:name":"Zowola Kpogu\u00e9d\u00e9",
    "gn:population":0,
    "gn:timezone":"Africa/Lome",
    "iso:country":"TG",
    "name:und_x_variant":[
        "Soholo",
        "Zowla",
        "Seluga",
        "Zowola Kpogere",
        "Zoola Kpogu\u00e9d\u00e9",
        "Zowola Kpogu\u00e9d\u00e9"
    ],
    "wof:name":"Zowola Kpoguede",
    "wof:placetype":"locality"
},
  "geometry": {"coordinates":[1.58333,6.28333],"type":"Point"}
}