{
  "type": "Feature",
  "properties": {
    "gn:admin1_code":"0.0",
    "gn:asciiname":"Tekpo",
    "gn:country_code":"TG",
    "gn:dem":91,
    "gn:feature_class":"P",
    "gn:feature_code":"PPL",
    "gn:name":"T\u00e9kpo",
    "gn:population":0,
    "gn:timezone":"Africa/Lome",
    "iso:country":"TG",
    "wof:name":"Tekpo",
    "wof:placetype":"locality"
},
  "geometry": {"coordinates":[1.18333,6.38333],"type":"Point"}
}