{
  "type": "Feature",
  "properties": {
    "gn:admin1_code":"24.0",
    "gn:asciiname":"Dekpo",
    "gn:country_code":"TG",
    "gn:dem":44,
    "gn:feature_class":"P",
    "gn:feature_code":"PPL",
    "gn:name":"D\u00e9kpo",
    "gn:population":0,
    "gn:timezone":"Africa/Lome",
    "iso:country":"TG",
    "wof:name":"Dekpo",
    "wof:placetype":"locality"
},
  "geometry": {"coordinates":[1.07833,6.45861],"type":"Point"}
}