{
  "type": "Feature",
  "properties": {
    "gn:admin1_code":"0.0",
    "gn:asciiname":"Toulong",
    "gn:country_code":"TG",
    "gn:dem":304,
    "gn:feature_class":"P",
    "gn:feature_code":"PPL",
    "gn:name":"Toulong",
    "gn:population":0,
    "gn:timezone":"Africa/Lome",
    "iso:country":"TG",
    "wof:name":"Toulong",
    "wof:placetype":"locality"
},
  "geometry": {"coordinates":[0.13333,10.86667],"type":"Point"}
}