{
  "type": "Feature",
  "properties": {
    "gn:admin1_code":"0.0",
    "gn:asciiname":"Atake",
    "gn:country_code":"TG",
    "gn:dem":150,
    "gn:feature_class":"P",
    "gn:feature_code":"PPL",
    "gn:name":"Atak\u00e9",
    "gn:population":0,
    "gn:timezone":"Africa/Lome",
    "iso:country":"TG",
    "wof:name":"Atake",
    "wof:placetype":"locality"
},
  "geometry": {"coordinates":[1.36667,7.36667],"type":"Point"}
}