{
  "type": "Feature",
  "properties": {
    "gn:admin1_code":"0.0",
    "gn:asciiname":"Bassoutougou",
    "gn:cc2":"TG",
    "gn:country_code":"TG",
    "gn:dem":252,
    "gn:feature_class":"P",
    "gn:feature_code":"PPL",
    "gn:name":"Bassoutougou",
    "gn:population":0,
    "gn:timezone":"Africa/Lome",
    "iso:country":"TG",
    "name:und_x_variant":[
        "Basoudougou",
        "Bassoutougou"
    ],
    "wof:name":"Bassoutougou",
    "wof:placetype":"locality"
},
  "geometry": {"coordinates":[0.05,10.95],"type":"Point"}
}