{
  "type": "Feature",
  "properties": {
    "gn:admin1_code":"0.0",
    "gn:asciiname":"Avedje",
    "gn:cc2":"TG",
    "gn:country_code":"TG",
    "gn:dem":130,
    "gn:feature_class":"P",
    "gn:feature_code":"PPL",
    "gn:name":"Av\u00e9dj\u00e9",
    "gn:population":0,
    "gn:timezone":"Africa/Lome",
    "iso:country":"TG",
    "name:und_x_variant":[
        "Avedio",
        "Av\u00e9dj\u00e9"
    ],
    "wof:name":"Avedje",
    "wof:placetype":"locality"
},
  "geometry": {"coordinates":[0.91667,6.73333],"type":"Point"}
}