{
  "type": "Feature",
  "properties": {
    "gn:admin1_code":"0.0",
    "gn:asciiname":"Afokponoe",
    "gn:country_code":"TG",
    "gn:dem":106,
    "gn:feature_class":"P",
    "gn:feature_code":"PPL",
    "gn:name":"Afokpono\u00e9",
    "gn:population":0,
    "gn:timezone":"Africa/Lome",
    "iso:country":"TG",
    "wof:name":"Afokponoe",
    "wof:placetype":"locality"
},
  "geometry": {"coordinates":[1.05,6.58333],"type":"Point"}
}