{
  "type": "Feature",
  "properties": {
    "gn:admin1_code":"0.0",
    "gn:asciiname":"Djigbe",
    "gn:country_code":"TG",
    "gn:dem":51,
    "gn:feature_class":"P",
    "gn:feature_code":"PPL",
    "gn:name":"Djigb\u00e9",
    "gn:population":0,
    "gn:timezone":"Africa/Lome",
    "iso:country":"TG",
    "wof:name":"Djigbe",
    "wof:placetype":"locality"
},
  "geometry": {"coordinates":[1.65,6.43333],"type":"Point"}
}