{
  "type": "Feature",
  "properties": {
    "gn:admin1_code":"0.0",
    "gn:asciiname":"Gdemeinkope",
    "gn:country_code":"TG",
    "gn:dem":156,
    "gn:feature_class":"P",
    "gn:feature_code":"PPL",
    "gn:name":"Gd\u00e9meinkop\u00e9",
    "gn:population":0,
    "gn:timezone":"Africa/Lome",
    "iso:country":"TG",
    "wof:name":"Gdemeinkope",
    "wof:placetype":"locality"
},
  "geometry": {"coordinates":[1.26667,7.01667],"type":"Point"}
}