{
  "type": "Feature",
  "properties": {
    "gn:admin1_code":"0.0",
    "gn:asciiname":"Logove",
    "gn:country_code":"TG",
    "gn:dem":54,
    "gn:feature_class":"P",
    "gn:feature_code":"PPL",
    "gn:name":"Logov\u00e9",
    "gn:population":0,
    "gn:timezone":"Africa/Lome",
    "iso:country":"TG",
    "wof:name":"Logove",
    "wof:placetype":"locality"
},
  "geometry": {"coordinates":[1.58333,6.43333],"type":"Point"}
}