{
  "type": "Feature",
  "properties": {
    "gn:admin1_code":"0.0",
    "gn:asciiname":"Kikpeou",
    "gn:country_code":"TG",
    "gn:dem":280,
    "gn:feature_class":"P",
    "gn:feature_code":"PPL",
    "gn:name":"Kikp\u00e9ou",
    "gn:population":0,
    "gn:timezone":"Africa/Lome",
    "iso:country":"TG",
    "name:und_x_variant":[
        "Kikp\u00e9ou"
    ],
    "wof:name":"Kikpeou",
    "wof:placetype":"locality"
},
  "geometry": {"coordinates":[0.78333,9.35],"type":"Point"}
}