{
  "type": "Feature",
  "properties": {
    "gn:admin1_code":"24.0",
    "gn:asciiname":"Adablai",
    "gn:country_code":"TG",
    "gn:dem":28,
    "gn:feature_class":"P",
    "gn:feature_code":"PPL",
    "gn:name":"Adablai",
    "gn:population":0,
    "gn:timezone":"Africa/Lome",
    "iso:country":"TG",
    "wof:name":"Adablai",
    "wof:placetype":"locality"
},
  "geometry": {"coordinates":[1.21917,6.20611],"type":"Point"}
}