{
  "type": "Feature",
  "properties": {
    "gn:admin1_code":"0.0",
    "gn:asciiname":"Dangma",
    "gn:country_code":"TG",
    "gn:dem":368,
    "gn:feature_class":"P",
    "gn:feature_code":"PPL",
    "gn:name":"Dangma",
    "gn:population":0,
    "gn:timezone":"Africa/Lome",
    "iso:country":"TG",
    "wof:name":"Dangma",
    "wof:placetype":"locality"
},
  "geometry": {"coordinates":[1.41667,9.05],"type":"Point"}
}