{
  "type": "Feature",
  "properties": {
    "gn:admin1_code":"0.0",
    "gn:asciiname":"Nandoundia",
    "gn:country_code":"TG",
    "gn:dem":167,
    "gn:feature_class":"P",
    "gn:feature_code":"PPL",
    "gn:name":"Nandoundia",
    "gn:population":0,
    "gn:timezone":"Africa/Lome",
    "iso:country":"TG",
    "wof:name":"Nandoundia",
    "wof:placetype":"locality"
},
  "geometry": {"coordinates":[0.75,9.88333],"type":"Point"}
}