{
  "type": "Feature",
  "properties": {
    "gn:admin1_code":"0.0",
    "gn:asciiname":"Adkepai Tchokoukon",
    "gn:country_code":"TG",
    "gn:dem":194,
    "gn:feature_class":"P",
    "gn:feature_code":"PPL",
    "gn:name":"Adk\u00e9pa\u00ef Tchokoukon",
    "gn:population":0,
    "gn:timezone":"Africa/Lome",
    "iso:country":"TG",
    "wof:name":"Adkepai Tchokoukon",
    "wof:placetype":"locality"
},
  "geometry": {"coordinates":[1.08333,7.31667],"type":"Point"}
}