{
  "type": "Feature",
  "properties": {
    "gn:admin1_code":"0.0",
    "gn:asciiname":"Rhlande",
    "gn:cc2":"TG",
    "gn:country_code":"TG",
    "gn:dem":13,
    "gn:feature_class":"P",
    "gn:feature_code":"PPL",
    "gn:name":"Rhland\u00e9",
    "gn:population":0,
    "gn:timezone":"Africa/Lome",
    "iso:country":"TG",
    "name:und_x_variant":[
        "Hland\u00e9",
        "Rhland\u00e9"
    ],
    "wof:name":"Rhlande",
    "wof:placetype":"locality"
},
  "geometry": {"coordinates":[1.73333,6.31667],"type":"Point"}
}