{
  "type": "Feature",
  "properties": {
    "gn:admin1_code":"24.0",
    "gn:asciiname":"Kletchi",
    "gn:country_code":"TG",
    "gn:dem":59,
    "gn:feature_class":"P",
    "gn:feature_code":"PPL",
    "gn:name":"Kl\u00e9tchi",
    "gn:population":0,
    "gn:timezone":"Africa/Lome",
    "iso:country":"TG",
    "name:und_x_variant":[
        "Kietchi",
        "Kl\u00e9ti",
        "Kl\u00e9tchi"
    ],
    "wof:name":"Kletchi",
    "wof:placetype":"locality"
},
  "geometry": {"coordinates":[1.44667,6.40833],"type":"Point"}
}