{
  "type": "Feature",
  "properties": {
    "gn:admin1_code":"0.0",
    "gn:asciiname":"Agou-Gare",
    "gn:country_code":"TG",
    "gn:dem":266,
    "gn:feature_class":"P",
    "gn:feature_code":"PPL",
    "gn:name":"Agou-Gare",
    "gn:population":0,
    "gn:timezone":"Africa/Lome",
    "iso:country":"TG",
    "wof:name":"Agou-Gare",
    "wof:placetype":"locality"
},
  "geometry": {"coordinates":[0.71667,6.85],"type":"Point"}
}