{
  "type": "Feature",
  "properties": {
    "gn:admin1_code":"24.0",
    "gn:asciiname":"Gatible",
    "gn:country_code":"TG",
    "gn:dem":47,
    "gn:feature_class":"P",
    "gn:feature_code":"PPL",
    "gn:name":"Gatibl\u00e9",
    "gn:population":0,
    "gn:timezone":"Africa/Lome",
    "iso:country":"TG",
    "wof:name":"Gatible",
    "wof:placetype":"locality"
},
  "geometry": {"coordinates":[1.07778,6.41611],"type":"Point"}
}