{
  "type": "Feature",
  "properties": {
    "gn:admin1_code":"0.0",
    "gn:asciiname":"Bedekope",
    "gn:country_code":"TG",
    "gn:dem":105,
    "gn:feature_class":"P",
    "gn:feature_code":"PPL",
    "gn:name":"B\u00e9d\u00e9kop\u00e9",
    "gn:population":0,
    "gn:timezone":"Africa/Lome",
    "iso:country":"TG",
    "wof:name":"Bedekope",
    "wof:placetype":"locality"
},
  "geometry": {"coordinates":[0.75,6.58333],"type":"Point"}
}