{
  "type": "Feature",
  "properties": {
    "gn:admin1_code":"0.0",
    "gn:asciiname":"Sante-Haut",
    "gn:country_code":"TG",
    "gn:dem":307,
    "gn:feature_class":"P",
    "gn:feature_code":"PPL",
    "gn:name":"Sant\u00e9-Haut",
    "gn:population":0,
    "gn:timezone":"Africa/Lome",
    "iso:country":"TG",
    "name:und_x_variant":[
        "Sant\u00e9-Haut"
    ],
    "wof:name":"Sante-Haut",
    "wof:placetype":"locality"
},
  "geometry": {"coordinates":[0.93333,9.48333],"type":"Point"}
}