{
  "type": "Feature",
  "properties": {
    "gn:admin1_code":"0.0",
    "gn:asciiname":"Namoute",
    "gn:country_code":"TG",
    "gn:dem":136,
    "gn:feature_class":"P",
    "gn:feature_code":"PPL",
    "gn:name":"Namout\u00e9",
    "gn:population":0,
    "gn:timezone":"Africa/Lome",
    "iso:country":"TG",
    "wof:name":"Namoute",
    "wof:placetype":"locality"
},
  "geometry": {"coordinates":[0.75,10.15],"type":"Point"}
}