{
  "type": "Feature",
  "properties": {
    "gn:admin1_code":"24.0",
    "gn:asciiname":"Tamanye",
    "gn:country_code":"TG",
    "gn:dem":3,
    "gn:feature_class":"P",
    "gn:feature_code":"PPL",
    "gn:name":"Tamany\u00e9",
    "gn:population":0,
    "gn:timezone":"Africa/Lome",
    "iso:country":"TG",
    "name:und_x_variant":[
        "Tamagn\u00e9",
        "Tamany\u00e9"
    ],
    "wof:name":"Tamanye",
    "wof:placetype":"locality"
},
  "geometry": {"coordinates":[1.31861,6.18306],"type":"Point"}
}