{
  "type": "Feature",
  "properties": {
    "gn:admin1_code":"0.0",
    "gn:asciiname":"Afitialakofe",
    "gn:country_code":"TG",
    "gn:dem":269,
    "gn:feature_class":"P",
    "gn:feature_code":"PPL",
    "gn:name":"Afitialakof\u00e9",
    "gn:population":0,
    "gn:timezone":"Africa/Lome",
    "iso:country":"TG",
    "wof:name":"Afitialakofe",
    "wof:placetype":"locality"
},
  "geometry": {"coordinates":[1.28333,8.45],"type":"Point"}
}