{
  "type": "Feature",
  "properties": {
    "gn:admin1_code":"0.0",
    "gn:asciiname":"Abalo Kpele",
    "gn:country_code":"TG",
    "gn:dem":201,
    "gn:feature_class":"P",
    "gn:feature_code":"PPL",
    "gn:name":"Abalo Kp\u00e9l\u00e9",
    "gn:population":0,
    "gn:timezone":"Africa/Lome",
    "iso:country":"TG",
    "wof:name":"Abalo Kpele",
    "wof:placetype":"locality"
},
  "geometry": {"coordinates":[1.58333,7.43333],"type":"Point"}
}