{
  "type": "Feature",
  "properties": {
    "gn:admin1_code":"24.0",
    "gn:asciiname":"Baka",
    "gn:country_code":"TG",
    "gn:dem":67,
    "gn:feature_class":"P",
    "gn:feature_code":"PPL",
    "gn:name":"Baka",
    "gn:population":0,
    "gn:timezone":"Africa/Lome",
    "iso:country":"TG",
    "wof:name":"Baka",
    "wof:placetype":"locality"
},
  "geometry": {"coordinates":[1.35389,6.16472],"type":"Point"}
}