{
  "type": "Feature",
  "properties": {
    "gn:admin1_code":"0.0",
    "gn:asciiname":"Kodji Kope",
    "gn:country_code":"TG",
    "gn:dem":41,
    "gn:feature_class":"P",
    "gn:feature_code":"PPL",
    "gn:name":"Kodji Kop\u00e9",
    "gn:population":0,
    "gn:timezone":"Africa/Lome",
    "iso:country":"TG",
    "wof:name":"Kodji Kope",
    "wof:placetype":"locality"
},
  "geometry": {"coordinates":[1.43333,6.53333],"type":"Point"}
}