{
  "type": "Feature",
  "properties": {
    "gn:admin1_code":"24.0",
    "gn:asciiname":"Dedje",
    "gn:country_code":"TG",
    "gn:dem":54,
    "gn:feature_class":"P",
    "gn:feature_code":"PPL",
    "gn:name":"D\u00e8dj\u00e9",
    "gn:population":0,
    "gn:timezone":"Africa/Lome",
    "iso:country":"TG",
    "name:und_x_variant":[
        "Zob\u00e9dji",
        "D\u00e8dj\u00e9"
    ],
    "wof:name":"Dedje",
    "wof:placetype":"locality"
},
  "geometry": {"coordinates":[1.09972,6.48667],"type":"Point"}
}