{
  "type": "Feature",
  "properties": {
    "gn:admin1_code":"0.0",
    "gn:asciiname":"Zogbepeme",
    "gn:cc2":"TG",
    "gn:country_code":"TG",
    "gn:dem":105,
    "gn:feature_class":"P",
    "gn:feature_code":"PPL",
    "gn:name":"Zogb\u00e9p\u00e9m\u00e9",
    "gn:population":0,
    "gn:timezone":"Africa/Lome",
    "iso:country":"TG",
    "name:und_x_variant":[
        "Sogbep\u00e9m\u00e9",
        "Zogb\u00e9pim\u00e9",
        "Zogb\u00e9p\u00e9m\u00e9"
    ],
    "wof:name":"Zogbepeme",
    "wof:placetype":"locality"
},
  "geometry": {"coordinates":[0.98333,6.45],"type":"Point"}
}