{
  "type": "Feature",
  "properties": {
    "gn:admin1_code":"0.0",
    "gn:asciiname":"Koussountou",
    "gn:cc2":"TG",
    "gn:country_code":"TG",
    "gn:dem":285,
    "gn:feature_class":"P",
    "gn:feature_code":"PPL",
    "gn:name":"Koussountou",
    "gn:population":0,
    "gn:timezone":"Africa/Lome",
    "iso:country":"TG",
    "name:und_x_variant":[
        "Kousountou",
        "Koussountou"
    ],
    "wof:name":"Koussountou",
    "wof:placetype":"locality"
},
  "geometry": {"coordinates":[0.61667,6.93333],"type":"Point"}
}