{
  "type": "Feature",
  "properties": {
    "gn:country":"TG",
    "gn:fcode":"PPL",
    "gn:pop":11466,
    "iso:country":"TG",
    "name:ceb_x_preferred":[
        "Kand\u00e9"
    ],
    "name:eng_x_preferred":[
        "Kand\u00e9"
    ],
    "name:fra_x_preferred":[
        "Kand\u00e9"
    ],
    "name:frr_x_preferred":[
        "Kand\u00e9"
    ],
    "name:ita_x_preferred":[
        "Kand\u00e9"
    ],
    "name:kbp_x_preferred":[
        "Kant\u025b"
    ],
    "name:lit_x_preferred":[
        "Kand\u0117"
    ],
    "name:nld_x_preferred":[
        "Kand\u00e9"
    ],
    "name:pol_x_preferred":[
        "Kand\u00e9"
    ],
    "name:ron_x_preferred":[
        "Kand\u00e9"
    ],
    "name:rus_x_preferred":[
        "\u041a\u0430\u043d\u0434\u0435"
    ],
    "name:spa_x_preferred":[
        "Kand\u00e9"
    ],
    "name:tur_x_preferred":[
        "Kand\u00e9"
    ],
    "name:unk_x_variant":[
        "Kant\u00e9"
    ],
    "name:zho_x_preferred":[
        "\u5eb7\u4ee3"
    ],
    "qs:name":"Kand\u00e9",
    "qs:photos_9r":0,
    "qs:photos_sr":0,
    "qs:pop_sr":"6",
    "wd:wordcount":73,
    "wof:name":"Kand\u00e9",
    "wof:placetype":"locality",
    "wof:population":11466
},
  "geometry": {"coordinates":[1.04472,9.95778],"type":"Point"}
}