{
  "type": "Feature",
  "properties": {
    "gn:admin1_code":"0.0",
    "gn:asciiname":"Soute",
    "gn:country_code":"TG",
    "gn:dem":165,
    "gn:feature_class":"P",
    "gn:feature_code":"PPL",
    "gn:name":"Sout\u00e9",
    "gn:population":0,
    "gn:timezone":"Africa/Lome",
    "iso:country":"TG",
    "wof:name":"Soute",
    "wof:placetype":"locality"
},
  "geometry": {"coordinates":[0.85,10.15],"type":"Point"}
}