{
  "type": "Feature",
  "properties": {
    "gn:admin1_code":"24.0",
    "gn:asciiname":"Adiseou",
    "gn:country_code":"TG",
    "gn:dem":66,
    "gn:feature_class":"P",
    "gn:feature_code":"PPL",
    "gn:name":"Adis\u00e9ou",
    "gn:population":0,
    "gn:timezone":"Africa/Lome",
    "iso:country":"TG",
    "wof:name":"Adiseou",
    "wof:placetype":"locality"
},
  "geometry": {"coordinates":[1.45194,6.19083],"type":"Point"}
}