{
  "type": "Feature",
  "properties": {
    "gn:admin1_code":"0.0",
    "gn:asciiname":"Pokpon",
    "gn:country_code":"TG",
    "gn:dem":148,
    "gn:feature_class":"P",
    "gn:feature_code":"PPL",
    "gn:name":"Pokpon",
    "gn:population":0,
    "gn:timezone":"Africa/Lome",
    "iso:country":"TG",
    "name:fra_x_preferred":[
        "Pokpon"
    ],
    "wof:name":"Pokpon",
    "wof:placetype":"locality"
},
  "geometry": {"coordinates":[0.73333,9.81667],"type":"Point"}
}