{
  "type": "Feature",
  "properties": {
    "gn:admin1_code":"0.0",
    "gn:asciiname":"Kountonri",
    "gn:country_code":"TG",
    "gn:dem":160,
    "gn:feature_class":"P",
    "gn:feature_code":"PPL",
    "gn:name":"Kountonri",
    "gn:population":0,
    "gn:timezone":"Africa/Lome",
    "iso:country":"TG",
    "wof:name":"Kountonri",
    "wof:placetype":"locality"
},
  "geometry": {"coordinates":[0.61667,10.11667],"type":"Point"}
}