{
  "type": "Feature",
  "properties": {
    "gn:admin1_code":"0.0",
    "gn:asciiname":"Abessankope",
    "gn:country_code":"TG",
    "gn:dem":179,
    "gn:feature_class":"P",
    "gn:feature_code":"PPL",
    "gn:name":"Ab\u00e9ssankop\u00e9",
    "gn:population":0,
    "gn:timezone":"Africa/Lome",
    "iso:country":"TG",
    "wof:name":"Abessankope",
    "wof:placetype":"locality"
},
  "geometry": {"coordinates":[1.15,7.36667],"type":"Point"}
}