{
  "type": "Feature",
  "properties": {
    "gn:admin1_code":"0.0",
    "gn:asciiname":"Laou",
    "gn:country_code":"TG",
    "gn:dem":351,
    "gn:feature_class":"P",
    "gn:feature_code":"PPL",
    "gn:name":"Laou",
    "gn:population":0,
    "gn:timezone":"Africa/Lome",
    "iso:country":"TG",
    "name:ceb_x_preferred":[
        "Laou"
    ],
    "name:fra_x_preferred":[
        "Laou"
    ],
    "name:urd_x_preferred":[
        "\u0644\u0627\u0648"
    ],
    "wof:name":"Laou",
    "wof:placetype":"locality"
},
  "geometry": {"coordinates":[0.93333,9.41667],"type":"Point"}
}