{
  "type": "Feature",
  "properties": {
    "gn:admin1_code":"0.0",
    "gn:asciiname":"Oronka",
    "gn:country_code":"TG",
    "gn:dem":227,
    "gn:feature_class":"P",
    "gn:feature_code":"PPL",
    "gn:name":"Oronka",
    "gn:population":0,
    "gn:timezone":"Africa/Lome",
    "iso:country":"TG",
    "wof:name":"Oronka",
    "wof:placetype":"locality"
},
  "geometry": {"coordinates":[1.05,7.31667],"type":"Point"}
}