{
  "type": "Feature",
  "properties": {
    "gn:admin1_code":"0.0",
    "gn:asciiname":"Kofelakou",
    "gn:country_code":"TG",
    "gn:dem":391,
    "gn:feature_class":"P",
    "gn:feature_code":"PPL",
    "gn:name":"Kof\u00e9lakou",
    "gn:population":0,
    "gn:timezone":"Africa/Lome",
    "iso:country":"TG",
    "wof:name":"Kofelakou",
    "wof:placetype":"locality"
},
  "geometry": {"coordinates":[1.13333,7.61667],"type":"Point"}
}