{
  "type": "Feature",
  "properties": {
    "gn:admin1_code":"0.0",
    "gn:asciiname":"Avoikope",
    "gn:country_code":"TG",
    "gn:dem":85,
    "gn:feature_class":"P",
    "gn:feature_code":"PPL",
    "gn:name":"Avoikop\u00e9",
    "gn:population":0,
    "gn:timezone":"Africa/Lome",
    "iso:country":"TG",
    "wof:name":"Avoikope",
    "wof:placetype":"locality"
},
  "geometry": {"coordinates":[0.76667,6.45],"type":"Point"}
}