{
  "type": "Feature",
  "properties": {
    "gn:admin1_code":"0.0",
    "gn:asciiname":"Agbodjekpwe",
    "gn:cc2":"TG",
    "gn:country_code":"TG",
    "gn:dem":102,
    "gn:feature_class":"P",
    "gn:feature_code":"PPL",
    "gn:name":"Agbodj\u00e9kpw\u00e9",
    "gn:population":0,
    "gn:timezone":"Africa/Lome",
    "iso:country":"TG",
    "name:und_x_variant":[
        "Agbodjekpoui",
        "Agbodj\u00e9kpw\u00e9"
    ],
    "wof:name":"Agbodjekpwe",
    "wof:placetype":"locality"
},
  "geometry": {"coordinates":[1.15,6.65],"type":"Point"}
}