{
  "type": "Feature",
  "properties": {
    "gn:admin1_code":"0.0",
    "gn:asciiname":"Attitogon",
    "gn:cc2":"TG",
    "gn:country_code":"TG",
    "gn:dem":46,
    "gn:feature_class":"P",
    "gn:feature_code":"PPL",
    "gn:name":"Attitogon",
    "gn:population":0,
    "gn:timezone":"Africa/Lome",
    "iso:country":"TG",
    "name:und_x_variant":[
        "Atitogon",
        "Atitogo",
        "Attitogon"
    ],
    "wof:name":"Attitogon",
    "wof:placetype":"locality"
},
  "geometry": {"coordinates":[1.66667,6.41667],"type":"Point"}
}