{
  "type": "Feature",
  "properties": {
    "gn:admin1_code":"0.0",
    "gn:asciiname":"Sodo",
    "gn:cc2":"TG",
    "gn:country_code":"TG",
    "gn:dem":445,
    "gn:feature_class":"P",
    "gn:feature_code":"PPL",
    "gn:name":"Sodo",
    "gn:population":0,
    "gn:timezone":"Africa/Lome",
    "iso:country":"TG",
    "name:und_x_variant":[
        "Ssodo",
        "Sodo"
    ],
    "wof:name":"Sodo",
    "wof:placetype":"locality"
},
  "geometry": {"coordinates":[0.81667,7.31667],"type":"Point"}
}