{
  "type": "Feature",
  "properties": {
    "gn:admin1_code":"0.0",
    "gn:asciiname":"Sodo",
    "gn:cc2":"TG",
    "gn:country_code":"TG",
    "gn:dem":445,
    "gn:feature_class":"P",
    "gn:feature_code":"PPL",
    "gn:name":"Sodo",
    "gn:population":0,
    "gn:timezone":"Africa/Lome",
    "iso:country":"TG",
    "name:ceb_x_preferred":[
        "Sodo"
    ],
    "name:deu_x_preferred":[
        "Soddo"
    ],
    "name:fra_x_preferred":[
        "Sodo"
    ],
    "name:heb_x_preferred":[
        "\u05e1\u05d5\u05d3\u05d5"
    ],
    "name:hrv_x_preferred":[
        "Sodo"
    ],
    "name:hun_x_preferred":[
        "Sodo"
    ],
    "name:ita_x_preferred":[
        "Soddo"
    ],
    "name:jav_x_preferred":[
        "Sodo"
    ],
    "name:nld_x_preferred":[
        "Sodo"
    ],
    "name:pol_x_preferred":[
        "Soddo"
    ],
    "name:rus_x_preferred":[
        "\u0421\u043e\u0434\u0434\u043e"
    ],
    "name:srp_x_preferred":[
        "\u0421\u043e\u0434\u043e"
    ],
    "name:und_x_variant":[
        "Ssodo"
    ],
    "wof:name":"Sodo",
    "wof:placetype":"locality"
},
  "geometry": {"coordinates":[0.81667,7.31667],"type":"Point"}
}