{
  "type": "Feature",
  "properties": {
    "gn:admin1_code":"0.0",
    "gn:asciiname":"Djonokouve",
    "gn:country_code":"TG",
    "gn:dem":6,
    "gn:feature_class":"P",
    "gn:feature_code":"PPL",
    "gn:name":"Djonokouv\u00e9",
    "gn:population":0,
    "gn:timezone":"Africa/Lome",
    "iso:country":"TG",
    "wof:name":"Djonokouve",
    "wof:placetype":"locality"
},
  "geometry": {"coordinates":[1.68333,6.48333],"type":"Point"}
}