{
  "type": "Feature",
  "properties": {
    "gn:admin1_code":"0.0",
    "gn:asciiname":"Niebodji",
    "gn:country_code":"TG",
    "gn:dem":159,
    "gn:feature_class":"P",
    "gn:feature_code":"PPL",
    "gn:name":"Ni\u00e9bodji",
    "gn:population":0,
    "gn:timezone":"Africa/Lome",
    "iso:country":"TG",
    "wof:name":"Niebodji",
    "wof:placetype":"locality"
},
  "geometry": {"coordinates":[1.53333,7.31667],"type":"Point"}
}