{
  "type": "Feature",
  "properties": {
    "gn:admin1_code":"0.0",
    "gn:asciiname":"Wotokou",
    "gn:country_code":"TG",
    "gn:dem":127,
    "gn:feature_class":"P",
    "gn:feature_code":"PPL",
    "gn:name":"Wotokou",
    "gn:population":0,
    "gn:timezone":"Africa/Lome",
    "iso:country":"TG",
    "wof:name":"Wotokou",
    "wof:placetype":"locality"
},
  "geometry": {"coordinates":[0.66667,6.75],"type":"Point"}
}