{
  "type": "Feature",
  "properties": {
    "gn:admin1_code":"0.0",
    "gn:asciiname":"Voukpo",
    "gn:cc2":"TG",
    "gn:country_code":"TG",
    "gn:dem":137,
    "gn:feature_class":"P",
    "gn:feature_code":"PPL",
    "gn:name":"Voukpo",
    "gn:population":0,
    "gn:timezone":"Africa/Lome",
    "iso:country":"TG",
    "name:und_x_variant":[
        "Woukpo",
        "Voukpo"
    ],
    "wof:name":"Voukpo",
    "wof:placetype":"locality"
},
  "geometry": {"coordinates":[0.85,6.68333],"type":"Point"}
}