{
  "type": "Feature",
  "properties": {
    "gn:admin1_code":"0.0",
    "gn:asciiname":"Voeve",
    "gn:country_code":"TG",
    "gn:dem":55,
    "gn:feature_class":"P",
    "gn:feature_code":"PPL",
    "gn:name":"Vo\u00e9v\u00e9",
    "gn:population":0,
    "gn:timezone":"Africa/Lome",
    "iso:country":"TG",
    "wof:name":"Voeve",
    "wof:placetype":"locality"
},
  "geometry": {"coordinates":[1.23333,6.38333],"type":"Point"}
}