{
  "type": "Feature",
  "properties": {
    "gn:admin1_code":"24.0",
    "gn:asciiname":"Tameklo",
    "gn:country_code":"TG",
    "gn:dem":31,
    "gn:feature_class":"P",
    "gn:feature_code":"PPL",
    "gn:name":"Tam\u00e9klo",
    "gn:population":0,
    "gn:timezone":"Africa/Lome",
    "iso:country":"TG",
    "wof:name":"Tameklo",
    "wof:placetype":"locality"
},
  "geometry": {"coordinates":[1.19417,6.20111],"type":"Point"}
}