{
  "type": "Feature",
  "properties": {
    "gn:admin1_code":"0.0",
    "gn:asciiname":"Atelo",
    "gn:country_code":"TG",
    "gn:dem":209,
    "gn:feature_class":"P",
    "gn:feature_code":"PPL",
    "gn:name":"At\u00e9lo",
    "gn:population":0,
    "gn:timezone":"Africa/Lome",
    "iso:country":"TG",
    "wof:name":"Atelo",
    "wof:placetype":"locality"
},
  "geometry": {"coordinates":[0.86667,9.91667],"type":"Point"}
}