{
  "type": "Feature",
  "properties": {
    "gn:admin1_code":"0.0",
    "gn:asciiname":"Djawaka",
    "gn:country_code":"TG",
    "gn:dem":143,
    "gn:feature_class":"P",
    "gn:feature_code":"PPL",
    "gn:name":"Djawaka",
    "gn:population":0,
    "gn:timezone":"Africa/Lome",
    "iso:country":"TG",
    "wof:name":"Djawaka",
    "wof:placetype":"locality"
},
  "geometry": {"coordinates":[0.51667,10.16667],"type":"Point"}
}