{
  "type": "Feature",
  "properties": {
    "gn:admin1_code":"0.0",
    "gn:asciiname":"Atontebou",
    "gn:country_code":"TG",
    "gn:dem":199,
    "gn:feature_class":"P",
    "gn:feature_code":"PPL",
    "gn:name":"Atont\u00e9bou",
    "gn:population":0,
    "gn:timezone":"Africa/Lome",
    "iso:country":"TG",
    "name:ceb_x_preferred":[
        "Atont\u00e9bou"
    ],
    "name:fra_x_preferred":[
        "Atontebou"
    ],
    "name:und_x_variant":[
        "Atont\u00e9bou"
    ],
    "wof:name":"Atontebou",
    "wof:placetype":"locality"
},
  "geometry": {"coordinates":[0.81667,9.86667],"type":"Point"}
}