{
  "type": "Feature",
  "properties": {
    "gn:admin1_code":"0.0",
    "gn:asciiname":"Sandiane",
    "gn:country_code":"TG",
    "gn:dem":267,
    "gn:feature_class":"P",
    "gn:feature_code":"PPL",
    "gn:name":"Sandiane",
    "gn:population":0,
    "gn:timezone":"Africa/Lome",
    "iso:country":"TG",
    "wof:name":"Sandiane",
    "wof:placetype":"locality"
},
  "geometry": {"coordinates":[1.06667,9.91667],"type":"Point"}
}