{
  "type": "Feature",
  "properties": {
    "gn:admin1_code":"0.0",
    "gn:asciiname":"Bouto",
    "gn:country_code":"TG",
    "gn:dem":210,
    "gn:feature_class":"P",
    "gn:feature_code":"PPL",
    "gn:name":"Bouto",
    "gn:population":0,
    "gn:timezone":"Africa/Lome",
    "iso:country":"TG",
    "wof:name":"Bouto",
    "wof:placetype":"locality"
},
  "geometry": {"coordinates":[1.16667,7.66667],"type":"Point"}
}